Workbook

Sheet Annual_Data
A1: company | B1: year | C1: scope1_mt_co2e | D1: scope2_location_mt_co2e | E1: employees_000 | F1: production_koebd_P | G1: production_net_koebd | H1: revenue_usd_millions_A | I1: total_energy_consumption_GWh | J1: total_energy_consumption_PJ | K1: post_acquisition | L1: sources | M1: notes
A2: BP | B2: 2021 | C2: 33.2 | D2: 2.4 | E2: 67 | F2: 2218 | G2: 2218 | H2: 157739 | I2: 128805 | J2: 463.698 | K2: 0 | L2: Revenue = sales and other operating revenues (bp Annual Report & 20-F 2025 income statement; 2021-22 from 20-F 2022). Production = total hydrocarbons net of royalties (KPI table, AR 2025). Employees 2023-25 from AR 2025. | M2: Production is net (bp does not publish operated production).
A3: BP | B3: 2022 | C3: 30.4 | D3: 1.4 | E3: 68 | F3: 2253 | G3: 2253 | H3: 241392 | I3: 121697 | J3: 438.1092 | K3: 0 | L3: Revenue = sales and other operating revenues (bp Annual Report & 20-F 2025 income statement; 2021-22 from 20-F 2022). Production = total hydrocarbons net of royalties (KPI table, AR 2025). Employees 2023-25 from AR 2025. | M3: Production is net (bp does not publish operated production).
A4: BP | B4: 2023 | C4: 31.1 | D4: 1 | E4: 87.8 | F4: 2313 | G4: 2313 | H4: 210130 | I4: 124770 | J4: 449.172 | K4: 0 | L4: Revenue = sales and other operating revenues (bp Annual Report & 20-F 2025 income statement; 2021-22 from 20-F 2022). Production = total hydrocarbons net of royalties (KPI table, AR 2025). Employees 2023-25 from AR 2025. | M4: Production is net (bp does not publish operated production).
A5: BP | B5: 2024 | C5: 32.8 | D5: 0.8 | E5: 100.5 | F5: 2358 | G5: 2358 | H5: 189185 | I5: 129872 | J5: 467.5392 | K5: 0 | L5: Revenue = sales and other operating revenues (bp Annual Report & 20-F 2025 income statement; 2021-22 from 20-F 2022). Production = total hydrocarbons net of royalties (KPI table, AR 2025). Employees 2023-25 from AR 2025. | M5: Production is net (bp does not publish operated production).
A6: BP | B6: 2025 | C6: 33.7 | D6: 0.7 | E6: 93.7 | F6: 2312 | G6: 2312 | H6: 189335 | I6: 134448 | J6: 484.0128 | K6: 0 | L6: Revenue = sales and other operating revenues (bp Annual Report & 20-F 2025 income statement; 2021-22 from 20-F 2022). Production = total hydrocarbons net of royalties (KPI table, AR 2025). Employees 2023-25 from AR 2025. | M6: Production is net (bp does not publish operated production).
A7: Chevron | B7: 2021 | C7: 57 | D7: 2 | E7: 37.5 | F7: 3099 | G7: 3099 | H7: 155606 | I7: 205833 | J7: 740.9988 | K7: 0 | L7: Revenue = sales and other operating revenues (10-K 2023-2025). Production = net oil-equivalent incl. affiliates (10-K 2021-2025). Energy = operated assets (Performance Data 2025). | M7: 2025 includes Hess (acquired Jul-2025). Scope 2 values match Chevron OPERATED market-based Scope 2 (location-based only reported from 2023).
A8: Chevron | B8: 2022 | C8: 53 | D8: 1 | E8: 38.3 | F8: 2999 | G8: 2999 | H8: 235717 | I8: 184167 | J8: 663.0012 | K8: 0 | L8: Revenue = sales and other operating revenues (10-K 2023-2025). Production = net oil-equivalent incl. affiliates (10-K 2021-2025). Energy = operated assets (Performance Data 2025). | M8: 2025 includes Hess (acquired Jul-2025). Scope 2 values match Chevron OPERATED market-based Scope 2 (location-based only reported from 2023).
A9: Chevron | B9: 2023 | C9: 52 | D9: 1 | E9: 40.2 | F9: 3120 | G9: 3120 | H9: 196913 | I9: 185278 | J9: 667.0008 | K9: 0 | L9: Revenue = sales and other operating revenues (10-K 2023-2025). Production = net oil-equivalent incl. affiliates (10-K 2021-2025). Energy = operated assets (Performance Data 2025). | M9: 2025 includes Hess (acquired Jul-2025). Scope 2 values match Chevron OPERATED market-based Scope 2 (location-based only reported from 2023).
A10: Chevron | B10: 2024 | C10: 53 | D10: 2 | E10: 41 | F10: 3338 | G10: 3338 | H10: 193414 | I10: 186944 | J10: 672.9984 | K10: 0 | L10: Revenue = sales and other operating revenues (10-K 2023-2025). Production = net oil-equivalent incl. affiliates (10-K 2021-2025). Energy = operated assets (Performance Data 2025). | M10: 2025 includes Hess (acquired Jul-2025). Scope 2 values match Chevron OPERATED market-based Scope 2 (location-based only reported from 2023).
A11: Chevron | B11: 2025 | C11: 55 | D11: 2 | E11: 43 | F11: 3723 | G11: 3723 | H11: 184432 | I11: 197778 | J11: 712.0008 | K11: 1 | L11: Revenue = sales and other operating revenues (10-K 2023-2025). Production = net oil-equivalent incl. affiliates (10-K 2021-2025). Energy = operated assets (Performance Data 2025). | M11: 2025 includes Hess (acquired Jul-2025). Scope 2 values match Chevron OPERATED market-based Scope 2 (location-based only reported from 2023).
A12: ConocoPhillips | B12: 2021 | C12: 17.7 | D12: 1.03 | E12: 10.4 | F12: 1901 | G12: 1567 | H12: 45828 | I12: 63596 | J12: 228.9456 | K12: 0 | L12: Revenue = sales and other operating revenues (10-K; 2025 consistent with Sustainability Report intensity metric). Production = Total Operated Production (Sustainability Report 2025 p.65) converted MMBOE/yr to kboe/d. Energy = operated total (p.62). | M12: P is OPERATED production to match operated emissions/energy; net production in production_net_koebd. 2025 includes Marathon Oil.
A13: ConocoPhillips | B13: 2022 | C13: 15 | D13: 1.06 | E13: 9.7 | F13: 1885 | G13: 1738 | H13: 78494 | I13: 60373 | J13: 217.3428 | K13: 0 | L13: Revenue = sales and other operating revenues (10-K; 2025 consistent with Sustainability Report intensity metric). Production = Total Operated Production (Sustainability Report 2025 p.65) converted MMBOE/yr to kboe/d. Energy = operated total (p.62). | M13: P is OPERATED production to match operated emissions/energy; net production in production_net_koebd. 2025 includes Marathon Oil.
... A26: ExxonMobil | B26: 2025 | C26: 90 | D26: 9 | E26: 58 | F26: 4736 | G26: 4736 | H26: 323905 | I26: 388889 | J26: 1400.0004 | K26: 1 | L26: Revenue = sales and other operating revenue (10-K 2022; Annual Report 2025). Production = net oil-equivalent production (results releases; AR 2025). Employees from AR 2025. | M26: 2024 onward includes Pioneer (acquired May-2024). Production is net. Energy rounded to 0.1 billion GJ in source.

Sheet Changes_Log
A1: company | B1: year | C1: variable | D1: old_value | E1: new_value | F1: change_%
A2: BP | B2: 2023 | C2: employees_000 | D2: 88 | E2: 87.8 | F2: =E2/D2-1 -> -0.0022727273
A3: BP | B3: 2024 | C3: employees_000 | D3: 101 | E3: 100.5 | F3: =E3/D3-1 -> -0.004950495
A4: BP | B4: 2025 | C4: employees_000 | D4: 102 | E4: 93.7 | F4: =E4/D4-1 -> -0.081372549
A5: ExxonMobil | B5: 2025 | C5: production_koebd_P | D5: 4738 | E5: 4736 | F5: =E5/D5-1 -> -0.00042211904

Sheet Monthly_Data
A1: company | B1: date | C1: year | D1: month | E1: days_in_month | F1: scope1_mt_co2e | G1: scope2_location_mt_co2e | H1: employees_000 | I1: production_koebd_P | J1: revenue_usd_millions_A | K1: total_energy_consumption_GWh | L1: total_energy_consumption_PJ | M1: energy_intensity_GWh_per_mmboe_T | N1: ln_scope1 | O1: ln_scope2 | P1: ln_P | Q1: ln_A | R1: ln_T | S1: post_acquisition | T1: data_type | U1: _sh_scope1 | V1: _sh_scope2 | W1: _sh_revenue | X1: _sh_energy | Y1: _fac_production
A2: BP | B2: 44197 | C2: 2021 | D2: 1 | E2: 31 | F2: =Annual_Data!$C$2*U2 -> 2.9591307 | G2: =Annual_Data!$D$2*V2 -> 0.22648699 | H2: =(2*Annual_Data!$E$2-Annual_Data!$E$3)+(Annual_Data!$E$2-(2*Annual_Data!$E$2-Annual_Data!$E$3))*D2/12 -> 66.083333 | I2: =Annual_Data!$F$2*Y2 -> 2218.4955 | J2: =Annual_Data!$H$2*W2 -> 11284.527 | K2: =Annual_Data!$I$2*X2 -> 11278.633 | L2: =K2*0.0036 -> 40.603079 | M2: =K2/(I2*E2/1000) -> 163.99712 | N2: =LN(F2) -> 1.0848956 | O2: =LN(G2) -> -1.4850678 | P2: =LN(I2) -> 7.7045845 | Q2: =LN(J2) -> 9.3311878 | R2: =LN(M2) -> 5.0998489 | S2: 0 | T2: Disaggregated (from annual) | U2: 0.089130444 | V2: 0.094369578 | W2: 0.071539234 | X2: 0.087563628 | Y2: 1.0002234
A3: BP | B3: 44228 | C3: 2021 | D3: 2 | E3: 28 | F3: =Annual_Data!$C$2*U3 -> 2.6150893 | G3: =Annual_Data!$D$2*V3 -> 0.21262802 | H3: =(2*Annual_Data!$E$2-Annual_Data!$E$3)+(Annual_Data!$E$2-(2*Annual_Data!$E$2-Annual_Data!$E$3))*D3/12 -> 66.166667 | I3: =Annual_Data!$F$2*Y3 -> 2206.5066 | J3: =Annual_Data!$H$2*W3 -> 10342.604 | K3: =Annual_Data!$I$2*X3 -> 10097.048 | L3: =K3*0.0036 -> 36.349373 | M3: =K3/(I3*E3/1000) -> 163.42977 | N3: =LN(F3) -> 0.96129824 | O3: =LN(G3) -> -1.548211 | P3: =LN(I3) -> 7.6991658 | Q3: =LN(J3) -> 9.244027 | R3: =LN(M3) -> 5.0963834 | S3: 0 | T3: Disaggregated (from annual) | U3: 0.078767749 | V3: 0.08859501 | W3: 0.06556783 | X3: 0.078390188 | Y3: 0.99481811
A4: BP | B4: 44256 | C4: 2021 | D4: 3 | E4: 31 | F4: =Annual_Data!$C$2*U4 -> 2.8461041 | G4: =Annual_Data!$D$2*V4 -> 0.22672686 | H4: =(2*Annual_Data!$E$2-Annual_Data!$E$3)+(Annual_Data!$E$2-(2*Annual_Data!$E$2-Annual_Data!$E$3))*D4/12 -> 66.25 | I4: =Annual_Data!$F$2*Y4 -> 2178.2285 | J4: =Annual_Data!$H$2*W4 -> 11213.906 | K4: =Annual_Data!$I$2*X4 -> 10923.514 | L4: =K4*0.0036 -> 39.32465 | M4: =K4/(I4*E4/1000) -> 161.76972 | N4: =LN(F4) -> 1.0459511 | O4: =LN(G4) -> -1.4840093 | P4: =LN(I4) -> 7.6862672 | Q4: =LN(J4) -> 9.3249099 | R4: =LN(M4) -> 5.0861738 | S4: 0 | T4: Disaggregated (from annual) | U4: 0.085726026 | V4: 0.094469523 | W4: 0.071091528 | X4: 0.084806598 | Y4: 0.98206876
A5: BP | B5: 44287 | C5: 2021 | D5: 4 | E5: 30 | F5: =Annual_Data!$C$2*U5 -> 2.7371786 | G5: =Annual_Data!$D$2*V5 -> 0.20525507 | H5: =(2*Annual_Data!$E$2-Annual_Data!$E$3)+(Annual_Data!$E$2-(2*Annual_Data!$E$2-Annual_Data!$E$3))*D5/12 -> 66.333333 | I5: =Annual_Data!$F$2*Y5 -> 2224.6546 | J5: =Annual_Data!$H$2*W5 -> 11434.03 | K5: =Annual_Data!$I$2*X5 -> 10506.961 | L5: =K5*0.0036 -> 37.825061 | M5: =K5/(I5*E5/1000) -> 157.4321 | N5: =LN(F5) -> 1.0069277 | O5: =LN(G5) -> -1.5835018 | P5: =LN(I5) -> 7.707357 | Q5: =LN(J5) -> 9.3443493 | R5: =LN(M5) -> 5.0589942 | S5: 0 | T5: Disaggregated (from annual) | U5: 0.082445139 | V5: 0.085522948 | W5: 0.072487019 | X5: 0.08157262 | Y5: 1.0030003
A6: BP | B6: 44317 | C6: 2021 | D6: 5 | E6: 31 | F6: =Annual_Data!$C$2*U6 -> 2.7894746 | G6: =Annual_Data!$D$2*V6 -> 0.20798983 | H6: =(2*Annual_Data!$E$2-Annual_Data!$E$3)+(Annual_Data!$E$2-(2*Annual_Data!$E$2-Annual_Data!$E$3))*D6/12 -> 66.416667 | I6: =Annual_Data!$F$2*Y6 -> 2239.2252 | J6: =Annual_Data!$H$2*W6 -> 12089.523 | K6: =Annual_Data!$I$2*X6 -> 10820.412 | L6: =K6*0.0036 -> 38.953484 | M6: =K6/(I6*E6/1000) -> 155.87782 | N6: =LN(F6) -> 1.0258533 | O6: =LN(G6) -> -1.5702661 | P6: =LN(I6) -> 7.7138852 | Q6: =LN(J6) -> 9.4000945 | R6: =LN(M6) -> 5.0490725 | S6: 0 | T6: Disaggregated (from annual) | U6: 0.084020319 | V6: 0.086662427 | W6: 0.076642572 | X6: 0.084006151 | Y6: 1.0095695
A7: BP | B7: 44348 | C7: 2021 | D7: 6 | E7: 30 | F7: =Annual_Data!$C$2*U7 -> 2.7171939 | G7: =Annual_Data!$D$2*V7 -> 0.20662766 | H7: =(2*Annual_Data!$E$2-Annual_Data!$E$3)+(Annual_Data!$E$2-(2*Annual_Data!$E$2-Annual_Data!$E$3))*D7/12 -> 66.5 | I7: =Annual_Data!$F$2*Y7 -> 2215.1213 | J7: =Annual_Data!$H$2*W7 -> 12257.07 | K7: =Annual_Data!$I$2*X7 -> 10537.962 | L7: =K7*0.0036 -> 37.936663 | M7: =K7/(I7*E7/1000) -> 158.57615 | N7: =LN(F7) -> 0.99959969 | O7: =LN(G7) -> -1.5768368 | P7: =LN(I7) -> 7.7030624 | Q7: =LN(J7) -> 9.4138582 | R7: =LN(M7) -> 5.0662349 | S7: 0 | T7: Disaggregated (from annual) | U7: 0.081843189 | V7: 0.086094859 | W7: 0.07770475 | X7: 0.081813299 | Y7: 0.9987021
A8: BP | B8: 44378 | C8: 2021 | D8: 7 | E8: 31 | F8: =Annual_Data!$C$2*U8 -> 2.8721222 | G8: =Annual_Data!$D$2*V8 -> 0.20972466 | H8: =(2*Annual_Data!$E$2-Annual_Data!$E$3)+(Annual_Data!$E$2-(2*Annual_Data!$E$2-Annual_Data!$E$3))*D8/12 -> 66.583333 | I8: =Annual_Data!$F$2*Y8 -> 2210.8952 | J8: =Annual_Data!$H$2*W8 -> 13145.918 | K8: =Annual_Data!$I$2*X8 -> 11099.534 | L8: =K8*0.0036 -> 39.958323 | M8: =K8/(I8*E8/1000) -> 161.94774 | N8: =LN(F8) -> 1.0550512 | O8: =LN(G8) -> -1.5619597 | P8: =LN(I8) -> 7.7011528 | Q8: =LN(J8) -> 9.4838665 | R8: =LN(M8) -> 5.0872737 | S8: 0 | T8: Disaggregated (from annual) | U8: 0.086509704 | V8: 0.087385276 | W8: 0.083339679 | X8: 0.086173162 | Y8: 0.99679677
A9: BP | B9: 44409 | C9: 2021 | D9: 8 | E9: 31 | F9: =Annual_Data!$C$2*U9 -> 2.8383934 | G9: =Annual_Data!$D$2*V9 -> 0.20814789 | H9: =(2*Annual_Data!$E$2-Annual_Data!$E$3)+(Annual_Data!$E$2-(2*Annual_Data!$E$2-Annual_Data!$E$3))*D9/12 -> 66.666667 | I9: =Annual_Data!$F$2*Y9 -> 2229.0791 | J9: =Annual_Data!$H$2*W9 -> 13797.038 | K9: =Annual_Data!$I$2*X9 -> 11044.436 | L9: =K9*0.0036 -> 39.759969 | M9: =K9/(I9*E9/1000) -> 159.82928 | N9: =LN(F9) -> 1.0432382 | O9: =LN(G9) -> -1.5695064 | P9: =LN(I9) -> 7.7093438 | Q9: =LN(J9) -> 9.5322092 | R9: =LN(M9) -> 5.0741063 | S9: 0 | T9: Disaggregated (from annual) | U9: 0.085493778 | V9: 0.086728287 | W9: 0.087467514 | X9: 0.085745397 | Y9: 1.0049951
A10: BP | B10: 44440 | C10: 2021 | D10: 9 | E10: 30 | F10: =Annual_Data!$C$2*U10 -> 2.6633677 | G10: =Annual_Data!$D$2*V10 -> 0.18588406 | H10: =(2*Annual_Data!$E$2-Annual_Data!$E$3)+(Annual_Data!$E$2-(2*Annual_Data!$E$2-Annual_Data!$E$3))*D10/12 -> 66.75 | I10: =Annual_Data!$F$2*Y10 -> 2208.4637 | J10: =Annual_Data!$H$2*W10 -> 14228.42 | K10: =Annual_Data!$I$2*X10 -> 10299.667 | L10: =K10*0.0036 -> 37.078803 | M10: =K10/(I10*E10/1000) -> 155.4575 | N10: =LN(F10) -> 0.97959137 | O10: =LN(G10) -> -1.6826321 | P10: =LN(I10) -> 7.7000524 | Q10: =LN(J10) -> 9.5629967 | R10: =LN(M10) -> 5.0463724 | S10: 0 | T10: Disaggregated (from annual) | U10: 0.080221919 | V10: 0.077451694 | W10: 0.090202298 | X10: 0.079963258 | Y10: 0.99570049
A11: BP | B11: 44470 | C11: 2021 | D11: 10 | E11: 31 | F11: =Annual_Data!$C$2*U11 -> 2.6608217 | G11: =Annual_Data!$D$2*V11 -> 0.17372924 | H11: =(2*Annual_Data!$E$2-Annual_Data!$E$3)+(Annual_Data!$E$2-(2*Annual_Data!$E$2-Annual_Data!$E$3))*D11/12 -> 66.833333 | I11: =Annual_Data!$F$2*Y11 -> 2214.4529 | J11: =Annual_Data!$H$2*W11 -> 15292.399 | K11: =Annual_Data!$I$2*X11 -> 10571.602 | L11: =K11*0.0036 -> 38.057766 | M11: =K11/(I11*E11/1000) -> 153.99714 | N11: =LN(F11) -> 0.97863497 | O11: =LN(G11) -> -1.7502573 | P11: =LN(I11) -> 7.7027607 | Q11: =LN(J11) -> 9.6351112 | R11: =LN(M11) -> 5.036934 | S11: 0 | T11: Disaggregated (from annual) | U11: 0.080145231 | V11: 0.072387185 | W11: 0.096947482 | X11: 0.082074467 | Y11: 0.99840079
A12: BP | B12: 44501 | C12: 2021 | D12: 11 | E12: 30 | F12: =Annual_Data!$C$2*U12 -> 2.6875419 | G12: =Annual_Data!$D$2*V12 -> 0.17084833 | H12: =(2*Annual_Data!$E$2-Annual_Data!$E$3)+(Annual_Data!$E$2-(2*Annual_Data!$E$2-Annual_Data!$E$3))*D12/12 -> 66.916667 | I12: =Annual_Data!$F$2*Y12 -> 2229.9671 | J12: =Annual_Data!$H$2*W12 -> 15578.704 | K12: =Annual_Data!$I$2*X12 -> 10570.317 | L12: =K12*0.0036 -> 38.053143 | M12: =K12/(I12*E12/1000) -> 158.00409 | N12: =LN(F12) -> 0.98862697 | O12: =LN(G12) -> -1.7669791 | P12: =LN(I12) -> 7.7097421 | Q12: =LN(J12) -> 9.6536601 | R12: =LN(M12) -> 5.0626209 | S12: 0 | T12: Disaggregated (from annual) | U12: 0.080950056 | V12: 0.071186802 | W12: 0.098762539 | X12: 0.082064496 | Y12: 1.0053954
A13: BP | B13: 44531 | C13: 2021 | D13: 12 | E13: 31 | F13: =Annual_Data!$C$2*U13 -> 2.813582 | G13: =Annual_Data!$D$2*V13 -> 0.16595139 | H13: =(2*Annual_Data!$E$2-Annual_Data!$E$3)+(Annual_Data!$E$2-(2*Annual_Data!$E$2-Annual_Data!$E$3))*D13/12 -> 67 | I13: =Annual_Data!$F$2*Y13 -> 2239.9982 | J13: =Annual_Data!$H$2*W13 -> 17074.861 | K13: =Annual_Data!$I$2*X13 -> 11054.913 | L13: =K13*0.0036 -> 39.797686 | M13: =K13/(I13*E13/1000) -> 159.20106 | N13: =LN(F13) -> 1.0344584 | O13: =LN(G13) -> -1.7960604 | P13: =LN(I13) -> 7.7142303 | Q13: =LN(J13) -> 9.7453625 | R13: =LN(M13) -> 5.070168 | S13: 0 | T13: Disaggregated (from annual) | U13: 0.084746445 | V13: 0.069146411 | W13: 0.10824755 | X13: 0.085826736 | Y13: 1.009918
A14: BP | B14: 44562 | C14: 2022 | D14: 1 | E14: 31 | F14: =Annual_Data!$C$3*U14 -> 2.7567105 | G14: =Annual_Data!$D$3*V14 -> 0.15986592 | H14: =Annual_Data!$E$2+(Annual_Data!$E$3-Annual_Data!$E$2)*D14/12 -> 67.083333 | I14: =Annual_Data!$F$3*Y14 -> 2238.0872 | J14: =Annual_Data!$H$3*W14 -> 17434.745 | K14: =Annual_Data!$I$3*X14 -> 10835.899 | L14: =K14*0.0036 -> 39.009236 | M14: =K14/(I14*E14/1000) -> 156.1803 | N14: =LN(F14) -> 1.0140381 | O14: =LN(G14) -> -1.8334198 | P14: =LN(I14) -> 7.7133768 | Q14: =LN(J14) -> 9.7662203 | R14: =LN(M14) -> 5.0510111 | S14: 0 | T14: Disaggregated (from annual) | U14: 0.090681267 | V14: 0.11418994 | W14: 0.07222586 | X14: 0.089039984 | Y14: 0.99338091
A15: BP | B15: 44593 | C15: 2022 | D15: 2 | E15: 28 | F15: =Annual_Data!$C$3*U15 -> 2.4101872 | G15: =Annual_Data!$D$3*V15 -> 0.12704987 | H15: =Annual_Data!$E$2+(Annual_Data!$E$3-Annual_Data!$E$2)*D15/12 -> 67.166667 | I15: =Annual_Data!$F$3*Y15 -> 2255.2158 | J15: =Annual_Data!$H$3*W15 -> 16803.586 | K15: =Annual_Data!$I$3*X15 -> 9559.4175 | L15: =K15*0.0036 -> 34.413903 | M15: =K15/(I15*E15/1000) -> 151.38586 | N15: =LN(F15) -> 0.87970442 | O15: =LN(G15) -> -2.0631756 | P15: =LN(I15) -> 7.7210009 | Q15: =LN(J15) -> 9.7293476 | R15: =LN(M15) -> 5.0198319 | S15: 0 | T15: Disaggregated (from annual) | U15: 0.079282473 | V15: 0.090749904 | W15: 0.069611197 | X15: 0.078550971 | Y15: 1.0009835
A16: BP | B16: 44621 | C16: 2022 | D16: 3 | E16: 31 | F16: =Annual_Data!$C$3*U16 -> 2.6284161 | G16: =Annual_Data!$D$3*V16 -> 0.13779602 | H16: =Annual_Data!$E$2+(Annual_Data!$E$3-Annual_Data!$E$2)*D16/12 -> 67.25 | I16: =Annual_Data!$F$3*Y16 -> 2252.1319 | J16: =Annual_Data!$H$3*W16 -> 19373.039 | K16: =Annual_Data!$I$3*X16 -> 10513.419 | L16: =K16*0.0036 -> 37.84831 | M16: =K16/(I16*E16/1000) -> 150.58734 | N16: =LN(F16) -> 0.96638144 | O16: =LN(G16) -> -1.9819808 | P16: =LN(I16) -> 7.7196326 | Q16: =LN(J16) -> 9.8716376 | R16: =LN(M16) -> 5.0145433 | S16: 0 | T16: Disaggregated (from annual) | U16: 0.086461057 | V16: 0.098425726 | W16: 0.080255515 | X16: 0.086390128 | Y16: 0.99961471
A17: BP | B17: 44652 | C17: 2022 | D17: 4 | E17: 30 | F17: =Annual_Data!$C$3*U17 -> 2.4639185 | G17: =Annual_Data!$D$3*V17 -> 0.12260714 | H17: =Annual_Data!$E$2+(Annual_Data!$E$3-Annual_Data!$E$2)*D17/12 -> 67.333333 | I17: =Annual_Data!$F$3*Y17 -> 2236.6905 | J17: =Annual_Data!$H$3*W17 -> 19944.499 | K17: =Annual_Data!$I$3*X17 -> 9878.8656 | L17: =K17*0.0036 -> 35.563916 | M17: =K17/(I17*E17/1000) -> 147.22445 | N17: =LN(F17) -> 0.90175298 | O17: =LN(G17) -> -2.09877 | P17: =LN(I17) -> 7.7127526 | Q17: =LN(J17) -> 9.9007087 | R17: =LN(M17) -> 4.9919583 | S17: 0 | T17: Disaggregated (from annual) | U17: 0.081049951 | V17: 0.087576529 | W17: 0.082622867 | X17: 0.081175918 | Y17: 0.99276096
A18: BP | B18: 44682 | C18: 2022 | D18: 5 | E18: 31 | F18: =Annual_Data!$C$3*U18 -> 2.4896306 | G18: =Annual_Data!$D$3*V18 -> 0.12052364 | H18: =Annual_Data!$E$2+(Annual_Data!$E$3-Annual_Data!$E$2)*D18/12 -> 67.416667 | I18: =Annual_Data!$F$3*Y18 -> 2235.9395 | J18: =Annual_Data!$H$3*W18 -> 21057.436 | K18: =Annual_Data!$I$3*X18 -> 9987.7432 | L18: =K18*0.0036 -> 35.955876 | M18: =K18/(I18*E18/1000) -> 144.09391 | N18: =LN(F18) -> 0.91213434 | O18: =LN(G18) -> -2.1159094 | P18: =LN(I18) -> 7.7124168 | Q18: =LN(J18) -> 9.955009 | R18: =LN(M18) -> 4.9704652 | S18: 0 | T18: Disaggregated (from annual) | U18: 0.081895743 | V18: 0.086088314 | W18: 0.087233364 | X18: 0.082070579 | Y18: 0.99242767
A19: BP | B19: 44713 | C19: 2022 | D19: 6 | E19: 30 | F19: =Annual_Data!$C$3*U19 -> 2.4870919 | G19: =Annual_Data!$D$3*V19 -> 0.12150603 | H19: =Annual_Data!$E$2+(Annual_Data!$E$3-Annual_Data!$E$2)*D19/12 -> 67.5 | I19: =Annual_Data!$F$3*Y19 -> 2263.4832 | J19: =Annual_Data!$H$3*W19 -> 20870.428 | K19: =Annual_Data!$I$3*X19 -> 9973.6289 | L19: =K19*0.0036 -> 35.905064 | M19: =K19/(I19*E19/1000) -> 146.8773 | N19: =LN(F19) -> 0.91111413 | O19: =LN(G19) -> -2.1077914 | P19: =LN(I19) -> 7.7246601 | Q19: =LN(J19) -> 9.9460885 | R19: =LN(M19) -> 4.9895975 | S19: 0 | T19: Disaggregated (from annual) | U19: 0.081812235 | V19: 0.086790018 | W19: 0.086458655 | X19: 0.081954599 | Y19: 1.004653
A20: BP | B20: 44743 | C20: 2022 | D20: 7 | E20: 31 | F20: =Annual_Data!$C$3*U20 -> 2.6045271 | G20: =Annual_Data!$D$3*V20 -> 0.11832447 | H20: =Annual_Data!$E$2+(Annual_Data!$E$3-Annual_Data!$E$2)*D20/12 -> 67.583333 | I20: =Annual_Data!$F$3*Y20 -> 2259.867 | J20: =Annual_Data!$H$3*W20 -> 22019.453 | K20: =Annual_Data!$I$3*X20 -> 10397.169 | L20: =K20*0.0036 -> 37.429809 | M20: =K20/(I20*E20/1000) -> 148.41252 | N20: =LN(F20) -> 0.95725114 | O20: =LN(G20) -> -2.1343246 | P20: =LN(I20) -> 7.7230612 | Q20: =LN(J20) -> 9.9996816 | R20: =LN(M20) -> 4.9999957 | S20: 0 | T20: Disaggregated (from annual) | U20: 0.085675235 | V20: 0.084517482 | W20: 0.091218652 | X20: 0.085434886 | Y20: 1.0030479
A21: BP | B21: 44774 | C21: 2022 | D21: 8 | E21: 31 | F21: =Annual_Data!$C$3*U21 -> 2.5278005 | G21: =Annual_Data!$D$3*V21 -> 0.10778913 | H21: =Annual_Data!$E$2+(Annual_Data!$E$3-Annual_Data!$E$2)*D21/12 -> 67.666667 | I21: =Annual_Data!$F$3*Y21 -> 2247.0133 | J21: =Annual_Data!$H$3*W21 -> 20474.734 | K21: =Annual_Data!$I$3*X21 -> 10196.19 | L21: =K21*0.0036 -> 36.706285 | M21: =K21/(I21*E21/1000) -> 146.37624 | N21: =LN(F21) -> 0.92734954 | O21: =LN(G21) -> -2.2275785 | P21: =LN(I21) -> 7.7173572 | Q21: =LN(J21) -> 9.9269469 | R21: =LN(M21) -> 4.9861803 | S21: 0 | T21: Disaggregated (from annual) | U21: 0.083151331 | V21: 0.076992233 | W21: 0.084819439 | X21: 0.083783415 | Y21: 0.99734277
A22: BP | B22: 44805 | C22: 2022 | D22: 9 | E22: 30 | F22: =Annual_Data!$C$3*U22 -> 2.3779343 | G22: =Annual_Data!$D$3*V22 -> 0.10419661 | H22: =Annual_Data!$E$2+(Annual_Data!$E$3-Annual_Data!$E$2)*D22/12 -> 67.75 | I22: =Annual_Data!$F$3*Y22 -> 2259.2965 | J22: =Annual_Data!$H$3*W22 -> 20600.562 | K22: =Annual_Data!$I$3*X22 -> 9638.4875 | L22: =K22*0.0036 -> 34.698555 | M22: =K22/(I22*E22/1000) -> 142.20485 | N22: =LN(F22) -> 0.86623218 | O22: =LN(G22) -> -2.2614757 | P22: =LN(I22) -> 7.7228088 | Q22: =LN(J22) -> 9.9330736 | R22: =LN(M22) -> 4.9572686 | S22: 0 | T22: Disaggregated (from annual) | U22: 0.078221524 | V22: 0.074426149 | W22: 0.085340699 | X22: 0.079200699 | Y22: 1.0027947
A23: BP | B23: 44835 | C23: 2022 | D23: 10 | E23: 31 | F23: =Annual_Data!$C$3*U23 -> 2.4676889 | G23: =Annual_Data!$D$3*V23 -> 0.0914358 | H23: =Annual_Data!$E$2+(Annual_Data!$E$3-Annual_Data!$E$2)*D23/12 -> 67.833333 | I23: =Annual_Data!$F$3*Y23 -> 2261.786 | J23: =Annual_Data!$H$3*W23 -> 21391.534 | K23: =Annual_Data!$I$3*X23 -> 9962.3742 | L23: =K23*0.0036 -> 35.864547 | M23: =K23/(I23*E23/1000) -> 142.08546 | N23: =LN(F23) -> 0.90328205 | O23: =LN(G23) -> -2.3921182 | P23: =LN(I23) -> 7.7239101 | Q23: =LN(J23) -> 9.9707505 | R23: =LN(M23) -> 4.9564287 | S23: 0 | T23: Disaggregated (from annual) | U23: 0.081173977 | V23: 0.065311286 | W23: 0.088617409 | X23: 0.081862118 | Y23: 1.0038997
A24: BP | B24: 44866 | C24: 2022 | D24: 11 | E24: 30 | F24: =Annual_Data!$C$3*U24 -> 2.5065082 | G24: =Annual_Data!$D$3*V24 -> 0.091630294 | H24: =Annual_Data!$E$2+(Annual_Data!$E$3-Annual_Data!$E$2)*D24/12 -> 67.916667 | I24: =Annual_Data!$F$3*Y24 -> 2251.0685 | J24: =Annual_Data!$H$3*W24 -> 20253.748 | K24: =Annual_Data!$I$3*X24 -> 10070.695 | L24: =K24*0.0036 -> 36.254501 | M24: =K24/(I24*E24/1000) -> 149.12466 | N24: =LN(F24) -> 0.91889064 | O24: =LN(G24) -> -2.3899933 | P24: =LN(I24) -> 7.7191603 | Q24: =LN(J24) -> 9.9160951 | R24: =LN(M24) -> 5.0047826 | S24: 0 | T24: Disaggregated (from annual) | U24: 0.082450929 | V24: 0.06545021 | W24: 0.083903972 | X24: 0.082752202 | Y24: 0.9991427
A25: BP | B25: 44896 | C25: 2022 | D25: 12 | E25: 31 | F25: =Annual_Data!$C$3*U25 -> 2.6795861 | G25: =Annual_Data!$D$3*V25 -> 0.09727509 | H25: =Annual_Data!$E$2+(Annual_Data!$E$3-Annual_Data!$E$2)*D25/12 -> 68 | I25: =Annual_Data!$F$3*Y25 -> 2275.588 | J25: =Annual_Data!$H$3*W25 -> 21168.237 | K25: =Annual_Data!$I$3*X25 -> 10683.11 | L25: =K25*0.0036 -> 38.459197 | M25: =K25/(I25*E25/1000) -> 151.44062 | N25: =LN(F25) -> 0.98566233 | O25: =LN(G25) -> -2.3302123 | P25: =LN(I25) -> 7.7299937 | Q25: =LN(J25) -> 9.9602571 | R25: =LN(M25) -> 5.0201936 | S25: 0 | T25: Disaggregated (from annual) | U25: 0.088144278 | V25: 0.069482207 | W25: 0.087692371 | X25: 0.087784501 | Y25: 1.0100257
A26: BP | B26: 44927 | C26: 2023 | D26: 1 | E26: 31 | F26: =Annual_Data!$C$4*U26 -> 2.623375 | G26: =Annual_Data!$D$4*V26 -> 0.093487336 | H26: =Annual_Data!$E$3+(Annual_Data!$E$4-Annual_Data!$E$3)*D26/12 -> 69.65 | I26: =Annual_Data!$F$4*Y26 -> 2281.4184 | J26: =Annual_Data!$H$4*W26 -> 20929.783 | K26: =Annual_Data!$I$4*X26 -> 10567.189 | L26: =K26*0.0036 -> 38.041879 | M26: =K26/(I26*E26/1000) -> 149.41453 | N26: =LN(F26) -> 0.96446166 | O26: =LN(G26) -> -2.3699293 | P26: =LN(I26) -> 7.7325526 | Q26: =LN(J26) -> 9.9489284 | R26: =LN(M26) -> 5.0067245 | S26: 0 | T26: Disaggregated (from annual) | U26: 0.084352894 | V26: 0.093487336 | W26: 0.099603973 | X26: 0.084693346 | Y26: 0.98634606
A27: BP | B27: 44958 | C27: 2023 | D27: 2 | E27: 28 | F27: =Annual_Data!$C$4*U27 -> 2.3985302 | G27: =Annual_Data!$D$4*V27 -> 0.086394473 | H27: =Annual_Data!$E$3+(Annual_Data!$E$4-Annual_Data!$E$3)*D27/12 -> 71.3 | I27: =Annual_Data!$F$4*Y27 -> 2313.2871 | J27: =Annual_Data!$H$4*W27 -> 18106.026 | K27: =Annual_Data!$I$4*X27 -> 9653.4492 | L27: =K27*0.0036 -> 34.752417 | M27: =K27/(I27*E27/1000) -> 149.03729 | N27: =LN(F27) -> 0.87485613 | O27: =LN(G27) -> -2.4488316 | P27: =LN(I27) -> 7.7464248 | Q27: =LN(J27) -> 9.8040001 | R27: =LN(M27) -> 5.0041966 | S27: 0 | T27: Disaggregated (from annual) | U27: 0.077123157 | V27: 0.086394473 | W27: 0.08616583 | X27: 0.077369954 | Y27: 1.0001241
A28: BP | B28: 44986 | C28: 2023 | D28: 3 | E28: 31 | F28: =Annual_Data!$C$4*U28 -> 2.5821214 | G28: =Annual_Data!$D$4*V28 -> 0.089175974 | H28: =Annual_Data!$E$3+(Annual_Data!$E$4-Annual_Data!$E$3)*D28/12 -> 72.95 | I28: =Annual_Data!$F$4*Y28 -> 2282.8457 | J28: =Annual_Data!$H$4*W28 -> 19138.694 | K28: =Annual_Data!$I$4*X28 -> 10479.748 | L28: =K28*0.0036 -> 37.727092 | M28: =K28/(I28*E28/1000) -> 148.08551 | N28: =LN(F28) -> 0.9486113 | O28: =LN(G28) -> -2.4171436 | P28: =LN(I28) -> 7.7331781 | Q28: =LN(J28) -> 9.8594674 | R28: =LN(M28) -> 4.9977899 | S28: 0 | T28: Disaggregated (from annual) | U28: 0.08302641 | V28: 0.089175974 | W28: 0.091080255 | X28: 0.083992528 | Y28: 0.98696312
A29: BP | B29: 45017 | C29: 2023 | D29: 4 | E29: 30 | F29: =Annual_Data!$C$4*U29 -> 2.48615 | G29: =Annual_Data!$D$4*V29 -> 0.082849174 | H29: =Annual_Data!$E$3+(Annual_Data!$E$4-Annual_Data!$E$3)*D29/12 -> 74.6 | I29: =Annual_Data!$F$4*Y29 -> 2310.3702 | J29: =Annual_Data!$H$4*W29 -> 17638.017 | K29: =Annual_Data!$I$4*X29 -> 10044.018 | L29: =K29*0.0036 -> 36.158466 | M29: =K29/(I29*E29/1000) -> 144.91211 | N29: =LN(F29) -> 0.91073532 | O29: =LN(G29) -> -2.4907335 | P29: =LN(I29) -> 7.745163 | Q29: =LN(J29) -> 9.7778119 | R29: =LN(M29) -> 4.9761274 | S29: 0 | T29: Disaggregated (from annual) | U29: 0.079940514 | V29: 0.082849174 | W29: 0.083938597 | X29: 0.080500267 | Y29: 0.99886302
A30: BP | B30: 45047 | C30: 2023 | D30: 5 | E30: 31 | F30: =Annual_Data!$C$4*U30 -> 2.49739 | G30: =Annual_Data!$D$4*V30 -> 0.08251583 | H30: =Annual_Data!$E$3+(Annual_Data!$E$4-Annual_Data!$E$3)*D30/12 -> 76.25 | I30: =Annual_Data!$F$4*Y30 -> 2291.5927 | J30: =Annual_Data!$H$4*W30 -> 17517.56 | K30: =Annual_Data!$I$4*X30 -> 10129.986 | L30: =K30*0.0036 -> 36.46795 | M30: =K30/(I30*E30/1000) -> 142.59678 | N30: =LN(F30) -> 0.91524618 | O30: =LN(G30) -> -2.4947651 | P30: =LN(I30) -> 7.7370023 | Q30: =LN(J30) -> 9.7709591 | R30: =LN(M30) -> 4.9600209 | S30: 0 | T30: Disaggregated (from annual) | U30: 0.080301929 | V30: 0.08251583 | W30: 0.083365346 | X30: 0.081189276 | Y30: 0.99074478
A31: BP | B31: 45078 | C31: 2023 | D31: 6 | E31: 30 | F31: =Annual_Data!$C$4*U31 -> 2.5164257 | G31: =Annual_Data!$D$4*V31 -> 0.085891201 | H31: =Annual_Data!$E$3+(Annual_Data!$E$4-Annual_Data!$E$3)*D31/12 -> 77.9 | I31: =Annual_Data!$F$4*Y31 -> 2304.1981 | J31: =Annual_Data!$H$4*W31 -> 17291.236 | K31: =Annual_Data!$I$4*X31 -> 10118.884 | L31: =K31*0.0036 -> 36.427983 | M31: =K31/(I31*E31/1000) -> 146.3833 | N31: =LN(F31) -> 0.92283951 | O31: =LN(G31) -> -2.4546739 | P31: =LN(I31) -> 7.742488 | Q31: =LN(J31) -> 9.7579551 | R31: =LN(M31) -> 4.9862285 | S31: 0 | T31: Disaggregated (from annual) | U31: 0.080914008 | V31: 0.085891201 | W31: 0.082288279 | X31: 0.081100297 | Y31: 0.99619461
A32: BP | B32: 45108 | C32: 2023 | D32: 7 | E32: 31 | F32: =Annual_Data!$C$4*U32 -> 2.6545696 | G32: =Annual_Data!$D$4*V32 -> 0.085937701 | H32: =Annual_Data!$E$3+(Annual_Data!$E$4-Annual_Data!$E$3)*D32/12 -> 79.55 | I32: =Annual_Data!$F$4*Y32 -> 2298.2795 | J32: =Annual_Data!$H$4*W32 -> 17097.324 | K32: =Annual_Data!$I$4*X32 -> 10633.211 | L32: =K32*0.0036 -> 38.279559 | M32: =K32/(I32*E32/1000) -> 149.24503 | N32: =LN(F32) -> 0.97628252 | O32: =LN(G32) -> -2.4541327 | P32: =LN(I32) -> 7.7399161 | Q32: =LN(J32) -> 9.7466772 | R32: =LN(M32) -> 5.0055895 | S32: 0 | T32: Disaggregated (from annual) | U32: 0.085355935 | V32: 0.085937701 | W32: 0.08136546 | X32: 0.085222497 | Y32: 0.99363577
A33: BP | B33: 45139 | C33: 2023 | D33: 8 | E33: 31 | F33: =Annual_Data!$C$4*U33 -> 2.6912228 | G33: =Annual_Data!$D$4*V33 -> 0.082423396 | H33: =Annual_Data!$E$3+(Annual_Data!$E$4-Annual_Data!$E$3)*D33/12 -> 81.2 | I33: =Annual_Data!$F$4*Y33 -> 2302.8897 | J33: =Annual_Data!$H$4*W33 -> 16673.44 | K33: =Annual_Data!$I$4*X33 -> 10787.124 | L33: =K33*0.0036 -> 38.833648 | M33: =K33/(I33*E33/1000) -> 151.10222 | N33: =LN(F33) -> 0.98999567 | O33: =LN(G33) -> -2.4958859 | P33: =LN(I33) -> 7.74192 | Q33: =LN(J33) -> 9.7215723 | R33: =LN(M33) -> 5.0179566 | S33: 0 | T33: Disaggregated (from annual) | U33: 0.086534496 | V33: 0.082423396 | W33: 0.079348215 | X33: 0.086456075 | Y33: 0.99562894
A34: BP | B34: 45170 | C34: 2023 | D34: 9 | E34: 30 | F34: =Annual_Data!$C$4*U34 -> 2.5753119 | G34: =Annual_Data!$D$4*V34 -> 0.080803332 | H34: =Annual_Data!$E$3+(Annual_Data!$E$4-Annual_Data!$E$3)*D34/12 -> 82.85 | I34: =Annual_Data!$F$4*Y34 -> 2320.807 | J34: =Annual_Data!$H$4*W34 -> 16355.478 | K34: =Annual_Data!$I$4*X34 -> 10195.52 | L34: =K34*0.0036 -> 36.703874 | M34: =K34/(I34*E34/1000) -> 146.43643 | N34: =LN(F34) -> 0.94597065 | O34: =LN(G34) -> -2.5157371 | P34: =LN(I34) -> 7.7496702 | Q34: =LN(J34) -> 9.7023182 | R34: =LN(M34) -> 4.9865914 | S34: 0 | T34: Disaggregated (from annual) | U34: 0.082807457 | V34: 0.080803332 | W34: 0.077835046 | X34: 0.081714518 | Y34: 1.0033753
A35: BP | B35: 45200 | C35: 2023 | D35: 10 | E35: 31 | F35: =Annual_Data!$C$4*U35 -> 2.6393491 | G35: =Annual_Data!$D$4*V35 -> 0.075091476 | H35: =Annual_Data!$E$3+(Annual_Data!$E$4-Annual_Data!$E$3)*D35/12 -> 84.5 | I35: =Annual_Data!$F$4*Y35 -> 2364.1505 | J35: =Annual_Data!$H$4*W35 -> 16924.393 | K35: =Annual_Data!$I$4*X35 -> 10532.641 | L35: =K35*0.0036 -> 37.917506 | M35: =K35/(I35*E35/1000) -> 143.71446 | N35: =LN(F35) -> 0.97053232 | O35: =LN(G35) -> -2.5890482 | P35: =LN(I35) -> 7.768174 | Q35: =LN(J35) -> 9.7365112 | R35: =LN(M35) -> 4.9678284 | S35: 0 | T35: Disaggregated (from annual) | U35: 0.084866529 | V35: 0.075091476 | W35: 0.080542486 | X35: 0.084416451 | Y35: 1.0221143
A36: BP | B36: 45231 | C36: 2023 | D36: 11 | E36: 30 | F36: =Annual_Data!$C$4*U36 -> 2.6279066 | G36: =Annual_Data!$D$4*V36 -> 0.07355237 | H36: =Annual_Data!$E$3+(Annual_Data!$E$4-Annual_Data!$E$3)*D36/12 -> 86.15 | I36: =Annual_Data!$F$4*Y36 -> 2333.9016 | J36: =Annual_Data!$H$4*W36 -> 16149.357 | K36: =Annual_Data!$I$4*X36 -> 10502.006 | L36: =K36*0.0036 -> 37.807223 | M36: =K36/(I36*E36/1000) -> 149.99213 | N36: =LN(F36) -> 0.96618758 | O36: =LN(G36) -> -2.6097576 | P36: =LN(I36) -> 7.7552967 | Q36: =LN(J36) -> 9.6896355 | R36: =LN(M36) -> 5.0105828 | S36: 0 | T36: Disaggregated (from annual) | U36: 0.084498606 | V36: 0.07355237 | W36: 0.076854124 | X36: 0.084170925 | Y36: 1.0090366
A37: BP | B37: 45261 | C37: 2023 | D37: 12 | E37: 31 | F37: =Annual_Data!$C$4*U37 -> 2.8076478 | G37: =Annual_Data!$D$4*V37 -> 0.081877738 | H37: =Annual_Data!$E$3+(Annual_Data!$E$4-Annual_Data!$E$3)*D37/12 -> 87.8 | I37: =Annual_Data!$F$4*Y37 -> 2352.8446 | J37: =Annual_Data!$H$4*W37 -> 16308.692 | K37: =Annual_Data!$I$4*X37 -> 11126.223 | L37: =K37*0.0036 -> 40.054404 | M37: =K37/(I37*E37/1000) -> 152.5432 | N37: =LN(F37) -> 1.0323471 | O37: =LN(G37) -> -2.5025282 | P37: =LN(I37) -> 7.7633803 | Q37: =LN(J37) -> 9.6994535 | R37: =LN(M37) -> 5.0274478 | S37: 0 | T37: Disaggregated (from annual) | U37: 0.090278065 | V37: 0.081877738 | W37: 0.07761239 | X37: 0.089173867 | Y37: 1.0172264
A38: BP | B38: 45292 | C38: 2024 | D38: 1 | E38: 31 | F38: =Annual_Data!$C$5*U38 -> 2.7687906 | G38: =Annual_Data!$D$5*V38 -> 0.079413227 | H38: =Annual_Data!$E$4+(Annual_Data!$E$5-Annual_Data!$E$4)*D38/12 -> 88.858333 | I38: =Annual_Data!$F$5*Y38 -> 2335.569 | J38: =Annual_Data!$H$5*W38 -> 16158.917 | K38: =Annual_Data!$I$5*X38 -> 10975.519 | L38: =K38*0.0036 -> 39.511867 | M38: =K38/(I38*E38/1000) -> 151.59004 | N38: =LN(F38) -> 1.0184106 | O38: =LN(G38) -> -2.5330903 | P38: =LN(I38) -> 7.7560108 | Q38: =LN(J38) -> 9.6902273 | R38: =LN(M38) -> 5.0211797 | S38: 0 | T38: Disaggregated (from annual) | U38: 0.084414348 | V38: 0.099266534 | W38: 0.085413307 | X38: 0.084510277 | Y38: 0.99048728
A39: BP | B39: 45323 | C39: 2024 | D39: 2 | E39: 29 | F39: =Annual_Data!$C$5*U39 -> 2.5777969 | G39: =Annual_Data!$D$5*V39 -> 0.07044881 | H39: =Annual_Data!$E$4+(Annual_Data!$E$5-Annual_Data!$E$4)*D39/12 -> 89.916667 | I39: =Annual_Data!$F$5*Y39 -> 2332.7764 | J39: =Annual_Data!$H$5*W39 -> 15072.071 | K39: =Annual_Data!$I$5*X39 -> 10165.491 | L39: =K39*0.0036 -> 36.595766 | M39: =K39/(I39*E39/1000) -> 150.26479 | N39: =LN(F39) -> 0.94693514 | O39: =LN(G39) -> -2.6528689 | P39: =LN(I39) -> 7.7548144 | Q39: =LN(J39) -> 9.6205987 | R39: =LN(M39) -> 5.012399 | S39: 0 | T39: Disaggregated (from annual) | U39: 0.07859137 | V39: 0.088061012 | W39: 0.079668428 | X39: 0.078273151 | Y39: 0.98930297
A40: BP | B40: 45352 | C40: 2024 | D40: 3 | E40: 31 | F40: =Annual_Data!$C$5*U40 -> 2.7260892 | G40: =Annual_Data!$D$5*V40 -> 0.072370344 | H40: =Annual_Data!$E$4+(Annual_Data!$E$5-Annual_Data!$E$4)*D40/12 -> 90.975 | I40: =Annual_Data!$F$5*Y40 -> 2355.7061 | J40: =Annual_Data!$H$5*W40 -> 16198.896 | K40: =Annual_Data!$I$5*X40 -> 10825.198 | L40: =K40*0.0036 -> 38.970714 | M40: =K40/(I40*E40/1000) -> 148.23579 | N40: =LN(F40) -> 1.002868 | O40: =LN(G40) -> -2.6259587 | P40: =LN(I40) -> 7.7645958 | Q40: =LN(J40) -> 9.6926984 | R40: =LN(M40) -> 4.9988042 | S40: 0 | T40: Disaggregated (from annual) | U40: 0.083112475 | V40: 0.09046293 | W40: 0.085624632 | X40: 0.083352827 | Y40: 0.99902718
A41: BP | B41: 45383 | C41: 2024 | D41: 4 | E41: 30 | F41: =Annual_Data!$C$5*U41 -> 2.5896166 | G41: =Annual_Data!$D$5*V41 -> 0.063667186 | H41: =Annual_Data!$E$4+(Annual_Data!$E$5-Annual_Data!$E$4)*D41/12 -> 92.033333 | I41: =Annual_Data!$F$5*Y41 -> 2360.1682 | J41: =Annual_Data!$H$5*W41 -> 15300.592 | K41: =Annual_Data!$I$5*X41 -> 10401.938 | L41: =K41*0.0036 -> 37.446977 | M41: =K41/(I41*E41/1000) -> 146.90956 | N41: =LN(F41) -> 0.95150984 | O41: =LN(G41) -> -2.754086 | P41: =LN(I41) -> 7.7664882 | Q41: =LN(J41) -> 9.6356468 | R41: =LN(M41) -> 4.9898171 | S41: 0 | T41: Disaggregated (from annual) | U41: 0.078951726 | V41: 0.079583983 | W41: 0.080876346 | X41: 0.080093769 | Y41: 1.0009195
A42: BP | B42: 45413 | C42: 2024 | D42: 5 | E42: 31 | F42: =Annual_Data!$C$5*U42 -> 2.6905514 | G42: =Annual_Data!$D$5*V42 -> 0.067681357 | H42: =Annual_Data!$E$4+(Annual_Data!$E$5-Annual_Data!$E$4)*D42/12 -> 93.091667 | I42: =Annual_Data!$F$5*Y42 -> 2351.5449 | J42: =Annual_Data!$H$5*W42 -> 16355.103 | K42: =Annual_Data!$I$5*X42 -> 10628.446 | L42: =K42*0.0036 -> 38.262406 | M42: =K42/(I42*E42/1000) -> 145.79908 | N42: =LN(F42) -> 0.98974615 | O42: =LN(G42) -> -2.6929445 | P42: =LN(I42) -> 7.7628278 | Q42: =LN(J42) -> 9.7022953 | R42: =LN(M42) -> 4.9822295 | S42: 0 | T42: Disaggregated (from annual) | U42: 0.082029006 | V42: 0.084601696 | W42: 0.086450318 | X42: 0.081837856 | Y42: 0.99726248
A43: BP | B43: 45444 | C43: 2024 | D43: 6 | E43: 30 | F43: =Annual_Data!$C$5*U43 -> 2.6332309 | G43: =Annual_Data!$D$5*V43 -> 0.06756118 | H43: =Annual_Data!$E$4+(Annual_Data!$E$5-Annual_Data!$E$4)*D43/12 -> 94.15 | I43: =Annual_Data!$F$5*Y43 -> 2340.1029 | J43: =Annual_Data!$H$5*W43 -> 16072.468 | K43: =Annual_Data!$I$5*X43 -> 10532.077 | L43: =K43*0.0036 -> 37.915477 | M43: =K43/(I43*E43/1000) -> 150.02299 | N43: =LN(F43) -> 0.96821156 | O43: =LN(G43) -> -2.6947217 | P43: =LN(I43) -> 7.7579502 | Q43: =LN(J43) -> 9.684863 | R43: =LN(M43) -> 5.0107885 | S43: 0 | T43: Disaggregated (from annual) | U43: 0.080281429 | V43: 0.084451475 | W43: 0.084956353 | X43: 0.081095824 | Y43: 0.99241006
A44: BP | B44: 45474 | C44: 2024 | D44: 7 | E44: 31 | F44: =Annual_Data!$C$5*U44 -> 2.7789343 | G44: =Annual_Data!$D$5*V44 -> 0.070729078 | H44: =Annual_Data!$E$4+(Annual_Data!$E$5-Annual_Data!$E$4)*D44/12 -> 95.208333 | I44: =Annual_Data!$F$5*Y44 -> 2339.9373 | J44: =Annual_Data!$H$5*W44 -> 16040.98 | K44: =Annual_Data!$I$5*X44 -> 10980.425 | L44: =K44*0.0036 -> 39.529531 | M44: =K44/(I44*E44/1000) -> 151.37469 | N44: =LN(F44) -> 1.0220675 | O44: =LN(G44) -> -2.6488985 | P44: =LN(I44) -> 7.7578794 | Q44: =LN(J44) -> 9.682902 | R44: =LN(M44) -> 5.0197581 | S44: 0 | T44: Disaggregated (from annual) | U44: 0.084723607 | V44: 0.088411347 | W44: 0.084789913 | X44: 0.084548058 | Y44: 0.99233981
A45: BP | B45: 45505 | C45: 2024 | D45: 8 | E45: 31 | F45: =Annual_Data!$C$5*U45 -> 2.8637871 | G45: =Annual_Data!$D$5*V45 -> 0.067966152 | H45: =Annual_Data!$E$4+(Annual_Data!$E$5-Annual_Data!$E$4)*D45/12 -> 96.266667 | I45: =Annual_Data!$F$5*Y45 -> 2374.6108 | J45: =Annual_Data!$H$5*W45 -> 15564.494 | K45: =Annual_Data!$I$5*X45 -> 11247.316 | L45: =K45*0.0036 -> 40.490339 | M45: =K45/(I45*E45/1000) -> 152.78995 | N45: =LN(F45) -> 1.0521449 | O45: =LN(G45) -> -2.6887455 | P45: =LN(I45) -> 7.7725888 | Q45: =LN(J45) -> 9.6527475 | R45: =LN(M45) -> 5.0290641 | S45: 0 | T45: Disaggregated (from annual) | U45: 0.087310581 | V45: 0.08495769 | W45: 0.082271288 | X45: 0.086603089 | Y45: 1.0070444
A46: BP | B46: 45536 | C46: 2024 | D46: 9 | E46: 30 | F46: =Annual_Data!$C$5*U46 -> 2.6563689 | G46: =Annual_Data!$D$5*V46 -> 0.056223811 | H46: =Annual_Data!$E$4+(Annual_Data!$E$5-Annual_Data!$E$4)*D46/12 -> 97.325 | I46: =Annual_Data!$F$5*Y46 -> 2383.1875 | J46: =Annual_Data!$H$5*W46 -> 15540.64 | K46: =Annual_Data!$I$5*X46 -> 10605.859 | L46: =K46*0.0036 -> 38.181093 | M46: =K46/(I46*E46/1000) -> 148.34277 | N46: =LN(F46) -> 0.9769601 | O46: =LN(G46) -> -2.8784149 | P46: =LN(I46) -> 7.7761942 | Q46: =LN(J46) -> 9.6512138 | R46: =LN(M46) -> 4.9995256 | S46: 0 | T46: Disaggregated (from annual) | U46: 0.080986855 | V46: 0.070279764 | W46: 0.082145202 | X46: 0.081663939 | Y46: 1.0106817
A47: BP | B47: 45566 | C47: 2024 | D47: 10 | E47: 31 | F47: =Annual_Data!$C$5*U47 -> 2.7600292 | G47: =Annual_Data!$D$5*V47 -> 0.06154709 | H47: =Annual_Data!$E$4+(Annual_Data!$E$5-Annual_Data!$E$4)*D47/12 -> 98.383333 | I47: =Annual_Data!$F$5*Y47 -> 2370.2293 | J47: =Annual_Data!$H$5*W47 -> 15491.788 | K47: =Annual_Data!$I$5*X47 -> 10840.019 | L47: =K47*0.0036 -> 39.024068 | M47: =K47/(I47*E47/1000) -> 147.5292 | N47: =LN(F47) -> 1.0152413 | O47: =LN(G47) -> -2.7879527 | P47: =LN(I47) -> 7.770742 | Q47: =LN(J47) -> 9.6480654 | R47: =LN(M47) -> 4.9940261 | S47: 0 | T47: Disaggregated (from annual) | U47: 0.084147233 | V47: 0.076933863 | W47: 0.081886979 | X47: 0.083466943 | Y47: 1.0051863
A48: BP | B48: 45597 | C48: 2024 | D48: 11 | E48: 30 | F48: =Annual_Data!$C$5*U48 -> 2.829286 | G48: =Annual_Data!$D$5*V48 -> 0.05938954 | H48: =Annual_Data!$E$4+(Annual_Data!$E$5-Annual_Data!$E$4)*D48/12 -> 99.441667 | I48: =Annual_Data!$F$5*Y48 -> 2391.3591 | J48: =Annual_Data!$H$5*W48 -> 15188.643 | K48: =Annual_Data!$I$5*X48 -> 11105.522 | L48: =K48*0.0036 -> 39.979879 | M48: =K48/(I48*E48/1000) -> 154.8007 | N48: =LN(F48) -> 1.0400244 | O48: =LN(G48) -> -2.8236372 | P48: =LN(I48) -> 7.7796171 | Q48: =LN(J48) -> 9.6283033 | R48: =LN(M48) -> 5.0421385 | S48: 0 | T48: Disaggregated (from annual) | U48: 0.086258719 | V48: 0.074236924 | W48: 0.080284607 | X48: 0.085511287 | Y48: 1.0141472
A49: BP | B49: 45627 | C49: 2024 | D49: 12 | E49: 31 | F49: =Annual_Data!$C$5*U49 -> 2.9255189 | G49: =Annual_Data!$D$5*V49 -> 0.063002225 | H49: =Annual_Data!$E$4+(Annual_Data!$E$5-Annual_Data!$E$4)*D49/12 -> 100.5 | I49: =Annual_Data!$F$5*Y49 -> 2360.5623 | J49: =Annual_Data!$H$5*W49 -> 16200.408 | K49: =Annual_Data!$I$5*X49 -> 11564.19 | L49: =K49*0.0036 -> 41.631084 | M49: =K49/(I49*E49/1000) -> 158.02946 | N49: =LN(F49) -> 1.0734719 | O49: =LN(G49) -> -2.7645852 | P49: =LN(I49) -> 7.7666551 | Q49: =LN(J49) -> 9.6927917 | R49: =LN(M49) -> 5.0627815 | S49: 0 | T49: Disaggregated (from annual) | U49: 0.08919265 | V49: 0.078752781 | W49: 0.085632626 | X49: 0.089042981 | Y49: 1.0010866
A50: BP | B50: 45658 | C50: 2025 | D50: 1 | E50: 31 | F50: =Annual_Data!$C$6*U50 -> 2.9500749 | G50: =Annual_Data!$D$6*V50 -> 0.065047336 | H50: =Annual_Data!$E$5+(Annual_Data!$E$6-Annual_Data!$E$5)*D50/12 -> 99.933333 | I50: =Annual_Data!$F$6*Y50 -> 2350.3626 | J50: =Annual_Data!$H$6*W50 -> 16237.309 | K50: =Annual_Data!$I$6*X50 -> 11677.953 | L50: =K50*0.0036 -> 42.040629 | M50: =K50/(I50*E50/1000) -> 160.27661 | N50: =LN(F50) -> 1.0818306 | O50: =LN(G50) -> -2.73264 | P50: =LN(I50) -> 7.7623249 | Q50: =LN(J50) -> 9.6950669 | R50: =LN(M50) -> 5.0769011 | S50: 0 | T50: Disaggregated (from annual) | U50: 0.087539315 | V50: 0.092924766 | W50: 0.085759682 | X50: 0.086858507 | Y50: 1.0165928
A51: BP | B51: 45689 | C51: 2025 | D51: 2 | E51: 28 | F51: =Annual_Data!$C$6*U51 -> 2.6588322 | G51: =Annual_Data!$D$6*V51 -> 0.056377267 | H51: =Annual_Data!$E$5+(Annual_Data!$E$6-Annual_Data!$E$5)*D51/12 -> 99.366667 | I51: =Annual_Data!$F$6*Y51 -> 2369.5563 | J51: =Annual_Data!$H$6*W51 -> 14686.652 | K51: =Annual_Data!$I$6*X51 -> 10584.825 | L51: =K51*0.0036 -> 38.105371 | M51: =K51/(I51*E51/1000) -> 159.53598 | N51: =LN(F51) -> 0.97788699 | O51: =LN(G51) -> -2.8756893 | P51: =LN(I51) -> 7.770458 | Q51: =LN(J51) -> 9.5946944 | R51: =LN(M51) -> 5.0722695 | S51: 0 | T51: Disaggregated (from annual) | U51: 0.078897097 | V51: 0.080538953 | W51: 0.077569665 | X51: 0.078728024 | Y51: 1.0248946
A52: BP | B52: 45717 | C52: 2025 | D52: 3 | E52: 31 | F52: =Annual_Data!$C$6*U52 -> 2.9008368 | G52: =Annual_Data!$D$6*V52 -> 0.059977435 | H52: =Annual_Data!$E$5+(Annual_Data!$E$6-Annual_Data!$E$5)*D52/12 -> 98.8 | I52: =Annual_Data!$F$6*Y52 -> 2356.587 | J52: =Annual_Data!$H$6*W52 -> 15749.728 | K52: =Annual_Data!$I$6*X52 -> 11573.006 | L52: =K52*0.0036 -> 41.662823 | M52: =K52/(I52*E52/1000) -> 158.41672 | N52: =LN(F52) -> 1.0649992 | O52: =LN(G52) -> -2.8137869 | P52: =LN(I52) -> 7.7649697 | Q52: =LN(J52) -> 9.6645783 | R52: =LN(M52) -> 5.065229 | S52: 0 | T52: Disaggregated (from annual) | U52: 0.086078243 | V52: 0.08568205 | W52: 0.083184449 | X52: 0.086077935 | Y52: 1.019285
A53: BP | B53: 45748 | C53: 2025 | D53: 4 | E53: 30 | F53: =Annual_Data!$C$6*U53 -> 2.7580529 | G53: =Annual_Data!$D$6*V53 -> 0.053507548 | H53: =Annual_Data!$E$5+(Annual_Data!$E$6-Annual_Data!$E$5)*D53/12 -> 98.233333 | I53: =Annual_Data!$F$6*Y53 -> 2337.2139 | J53: =Annual_Data!$H$6*W53 -> 15365.563 | K53: =Annual_Data!$I$6*X53 -> 10808.751 | L53: =K53*0.0036 -> 38.911502 | M53: =K53/(I53*E53/1000) -> 154.15435 | N53: =LN(F53) -> 1.0145249 | O53: =LN(G53) -> -2.9279326 | P53: =LN(I53) -> 7.7567149 | Q53: =LN(J53) -> 9.6398841 | R53: =LN(M53) -> 5.0379544 | S53: 0 | T53: Disaggregated (from annual) | U53: 0.081841331 | V53: 0.076439354 | W53: 0.081155426 | X53: 0.08039354 | Y53: 1.0109057
A54: BP | B54: 45778 | C54: 2025 | D54: 5 | E54: 31 | F54: =Annual_Data!$C$6*U54 -> 2.7718204 | G54: =Annual_Data!$D$6*V54 -> 0.055515208 | H54: =Annual_Data!$E$5+(Annual_Data!$E$6-Annual_Data!$E$5)*D54/12 -> 97.666667 | I54: =Annual_Data!$F$6*Y54 -> 2319.152 | J54: =Annual_Data!$H$6*W54 -> 16070.706 | K54: =Annual_Data!$I$6*X54 -> 10999.551 | L54: =K54*0.0036 -> 39.598385 | M54: =K54/(I54*E54/1000) -> 152.99741 | N54: =LN(F54) -> 1.0195043 | O54: =LN(G54) -> -2.8910983 | P54: =LN(I54) -> 7.7489569 | Q54: =LN(J54) -> 9.6847534 | R54: =LN(M54) -> 5.030421 | S54: 0 | T54: Disaggregated (from annual) | U54: 0.082249863 | V54: 0.079307441 | W54: 0.08487974 | X54: 0.081812681 | Y54: 1.0030934
A55: BP | B55: 45809 | C55: 2025 | D55: 6 | E55: 30 | F55: =Annual_Data!$C$6*U55 -> 2.7676591 | G55: =Annual_Data!$D$6*V55 -> 0.058237054 | H55: =Annual_Data!$E$5+(Annual_Data!$E$6-Annual_Data!$E$5)*D55/12 -> 97.1 | I55: =Annual_Data!$F$6*Y55 -> 2303.2172 | J55: =Annual_Data!$H$6*W55 -> 15613.941 | K55: =Annual_Data!$I$6*X55 -> 10979.659 | L55: =K55*0.0036 -> 39.526771 | M55: =K55/(I55*E55/1000) -> 158.90322 | N55: =LN(F55) -> 1.0180019 | O55: =LN(G55) -> -2.8432335 | P55: =LN(I55) -> 7.7420622 | Q55: =LN(J55) -> 9.6559194 | R55: =LN(M55) -> 5.0682953 | S55: 0 | T55: Disaggregated (from annual) | U55: 0.082126383 | V55: 0.083195791 | W55: 0.082467272 | X55: 0.081664723 | Y55: 0.99620122
A56: BP | B56: 45839 | C56: 2025 | D56: 7 | E56: 31 | F56: =Annual_Data!$C$6*U56 -> 2.8734829 | G56: =Annual_Data!$D$6*V56 -> 0.061776226 | H56: =Annual_Data!$E$5+(Annual_Data!$E$6-Annual_Data!$E$5)*D56/12 -> 96.533333 | I56: =Annual_Data!$F$6*Y56 -> 2296.9682 | J56: =Annual_Data!$H$6*W56 -> 16204.95 | K56: =Annual_Data!$I$6*X56 -> 11492.999 | L56: =K56*0.0036 -> 41.374798 | M56: =K56/(I56*E56/1000) -> 161.4049 | N56: =LN(F56) -> 1.0555248 | O56: =LN(G56) -> -2.7842367 | P56: =LN(I56) -> 7.7393454 | Q56: =LN(J56) -> 9.693072 | R56: =LN(M56) -> 5.0839161 | S56: 0 | T56: Disaggregated (from annual) | U56: 0.085266554 | V56: 0.088251752 | W56: 0.085588772 | X56: 0.085482859 | Y56: 0.99349836
A57: BP | B57: 45870 | C57: 2025 | D57: 8 | E57: 31 | F57: =Annual_Data!$C$6*U57 -> 2.897438 | G57: =Annual_Data!$D$6*V57 -> 0.061600934 | H57: =Annual_Data!$E$5+(Annual_Data!$E$6-Annual_Data!$E$5)*D57/12 -> 95.966667 | I57: =Annual_Data!$F$6*Y57 -> 2275.5254 | J57: =Annual_Data!$H$6*W57 -> 16464.863 | K57: =Annual_Data!$I$6*X57 -> 11497.576 | L57: =K57*0.0036 -> 41.391275 | M57: =K57/(I57*E57/1000) -> 162.99074 | N57: =LN(F57) -> 1.0638269 | O57: =LN(G57) -> -2.7870783 | P57: =LN(I57) -> 7.7299662 | Q57: =LN(J57) -> 9.7089839 | R57: =LN(M57) -> 5.0936934 | S57: 0 | T57: Disaggregated (from annual) | U57: 0.085977389 | V57: 0.088001334 | W57: 0.086961539 | X57: 0.085516901 | Y57: 0.98422377
A58: BP | B58: 45901 | C58: 2025 | D58: 9 | E58: 30 | F58: =Annual_Data!$C$6*U58 -> 2.6843417 | G58: =Annual_Data!$D$6*V58 -> 0.056616327 | H58: =Annual_Data!$E$5+(Annual_Data!$E$6-Annual_Data!$E$5)*D58/12 -> 95.4 | I58: =Annual_Data!$F$6*Y58 -> 2276.5753 | J58: =Annual_Data!$H$6*W58 -> 15322.676 | K58: =Annual_Data!$I$6*X58 -> 10746.211 | L58: =K58*0.0036 -> 38.686359 | M58: =K58/(I58*E58/1000) -> 157.34469 | N58: =LN(F58) -> 0.98743554 | O58: =LN(G58) -> -2.8714579 | P58: =LN(I58) -> 7.7304275 | Q58: =LN(J58) -> 9.6370891 | R58: =LN(M58) -> 5.0584389 | S58: 0 | T58: Disaggregated (from annual) | U58: 0.079654058 | V58: 0.080880467 | W58: 0.080928913 | X58: 0.079928381 | Y58: 0.98467791
A59: BP | B59: 45931 | C59: 2025 | D59: 10 | E59: 31 | F59: =Annual_Data!$C$6*U59 -> 2.7441197 | G59: =Annual_Data!$D$6*V59 -> 0.056357846 | H59: =Annual_Data!$E$5+(Annual_Data!$E$6-Annual_Data!$E$5)*D59/12 -> 94.833333 | I59: =Annual_Data!$F$6*Y59 -> 2282.8802 | J59: =Annual_Data!$H$6*W59 -> 16155.486 | K59: =Annual_Data!$I$6*X59 -> 11045.293 | L59: =K59*0.0036 -> 39.763055 | M59: =K59/(I59*E59/1000) -> 156.07467 | N59: =LN(F59) -> 1.0094603 | O59: =LN(G59) -> -2.8760338 | P59: =LN(I59) -> 7.7331932 | Q59: =LN(J59) -> 9.690015 | R59: =LN(M59) -> 5.0503345 | S59: 0 | T59: Disaggregated (from annual) | U59: 0.081427884 | V59: 0.080511209 | W59: 0.085327521 | X59: 0.082152899 | Y59: 0.98740493
A60: BP | B60: 45962 | C60: 2025 | D60: 11 | E60: 30 | F60: =Annual_Data!$C$6*U60 -> 2.779098 | G60: =Annual_Data!$D$6*V60 -> 0.055061121 | H60: =Annual_Data!$E$5+(Annual_Data!$E$6-Annual_Data!$E$5)*D60/12 -> 94.266667 | I60: =Annual_Data!$F$6*Y60 -> 2299.3344 | J60: =Annual_Data!$H$6*W60 -> 15613.277 | K60: =Annual_Data!$I$6*X60 -> 11300.8 | L60: =K60*0.0036 -> 40.682882 | M60: =K60/(I60*E60/1000) -> 163.82713 | N60: =LN(F60) -> 1.0221264 | O60: =LN(G60) -> -2.8993114 | P60: =LN(I60) -> 7.740375 | Q60: =LN(J60) -> 9.6558769 | R60: =LN(M60) -> 5.0988118 | S60: 0 | T60: Disaggregated (from annual) | U60: 0.082465815 | V60: 0.078658745 | W60: 0.082463764 | X60: 0.084053318 | Y60: 0.99452179
A61: BP | B61: 45992 | C61: 2025 | D61: 12 | E61: 31 | F61: =Annual_Data!$C$6*U61 -> 2.9142435 | G61: =Annual_Data!$D$6*V61 -> 0.059925697 | H61: =Annual_Data!$E$5+(Annual_Data!$E$6-Annual_Data!$E$5)*D61/12 -> 93.7 | I61: =Annual_Data!$F$6*Y61 -> 2281.1762 | J61: =Annual_Data!$H$6*W61 -> 15849.85 | K61: =Annual_Data!$I$6*X61 -> 11741.375 | L61: =K61*0.0036 -> 42.26895 | M61: =K61/(I61*E61/1000) -> 166.03454 | N61: =LN(F61) -> 1.0696103 | O61: =LN(G61) -> -2.8146499 | P61: =LN(I61) -> 7.7324465 | Q61: =LN(J61) -> 9.6709153 | R61: =LN(M61) -> 5.1121958 | S61: 0 | T61: Disaggregated (from annual) | U61: 0.086476068 | V61: 0.085608138 | W61: 0.083713257 | X61: 0.087330232 | Y61: 0.98666792
A62: BP | B62: 46023 | C62: 2026 | D62: 1 | E62: 31 | F62: =Assumptions_2026!$G$2*U62 -> 2.9448448 | G62: =Assumptions_2026!$G$3*V62 -> 0.058284204 | H62: =Annual_Data!$E$6+(Assumptions_2026!$G$4-Annual_Data!$E$6)*D62/12 -> 94.382974 | I62: =Assumptions_2026!$G$5*Y62 -> 2304.2406 | J62: =Assumptions_2026!$G$6*W62 -> 15951.55 | K62: =Assumptions_2026!$G$7*X62 -> 11674.453 | L62: =K62*0.0036 -> 42.028032 | M62: =K62/(I62*E62/1000) -> 163.43574 | N62: =LN(F62) -> 1.0800561 | O62: =LN(G62) -> -2.8424242 | P62: =LN(I62) -> 7.7425064 | Q62: =LN(J62) -> 9.6773113 | R62: =LN(M62) -> 5.0964199 | S62: 0 | T62: Synthetic 2026 | U62: 0.087058175 | V62: 0.11330032 | W62: 0.080491317 | X62: 0.085906654 | Y62: 0.98635538
A63: BP | B63: 46054 | C63: 2026 | D63: 2 | E63: 28 | F63: =Assumptions_2026!$G$2*U63 -> 2.5867853 | G63: =Assumptions_2026!$G$3*V63 -> 0.050373086 | H63: =Annual_Data!$E$6+(Assumptions_2026!$G$4-Annual_Data!$E$6)*D63/12 -> 95.065947 | I63: =Assumptions_2026!$G$5*Y63 -> 2320.0004 | J63: =Assumptions_2026!$G$6*W63 -> 14807.781 | K63: =Assumptions_2026!$G$7*X63 -> 10536.207 | L63: =K63*0.0036 -> 37.930347 | M63: =K63/(I63*E63/1000) -> 162.19528 | N63: =LN(F63) -> 0.9504159 | O63: =LN(G63) -> -2.9882983 | P63: =LN(I63) -> 7.7493227 | Q63: =LN(J63) -> 9.602908 | R63: =LN(M63) -> 5.088801 | S63: 0 | T63: Synthetic 2026 | U63: 0.076472894 | V63: 0.097921671 | W63: 0.074719871 | X63: 0.077530853 | Y63: 0.99310156
A64: BP | B64: 46082 | C64: 2026 | D64: 3 | E64: 31 | F64: =Assumptions_2026!$G$2*U64 -> 2.8490257 | G64: =Assumptions_2026!$G$3*V64 -> 0.050020373 | H64: =Annual_Data!$E$6+(Assumptions_2026!$G$4-Annual_Data!$E$6)*D64/12 -> 95.748921 | I64: =Assumptions_2026!$G$5*Y64 -> 2316.283 | J64: =Assumptions_2026!$G$6*W64 -> 15836.691 | K64: =Assumptions_2026!$G$7*X64 -> 11431.899 | L64: =K64*0.0036 -> 41.154835 | M64: =K64/(I64*E64/1000) -> 159.20806 | N64: =LN(F64) -> 1.0469771 | O64: =LN(G64) -> -2.9953249 | P64: =LN(I64) -> 7.747719 | Q64: =LN(J64) -> 9.6700848 | R64: =LN(M64) -> 5.0702119 | S64: 0 | T64: Synthetic 2026 | U64: 0.084225483 | V64: 0.097236023 | W64: 0.079911741 | X64: 0.084121811 | Y64: 0.99151025
A65: BP | B65: 46113 | C65: 2026 | D65: 4 | E65: 30 | F65: =Assumptions_2026!$G$2*U65 -> 2.7320604 | G65: =Assumptions_2026!$G$3*V65 -> 0.046354427 | H65: =Annual_Data!$E$6+(Assumptions_2026!$G$4-Annual_Data!$E$6)*D65/12 -> 96.431895 | I65: =Assumptions_2026!$G$5*Y65 -> 2295.6493 | J65: =Assumptions_2026!$G$6*W65 -> 16059.668 | K65: =Assumptions_2026!$G$7*X65 -> 10898.429 | L65: =K65*0.0036 -> 39.234343 | M65: =K65/(I65*E65/1000) -> 158.24758 | N65: =LN(F65) -> 1.005056 | O65: =LN(G65) -> -3.0714385 | P65: =LN(I65) -> 7.738771 | Q65: =LN(J65) -> 9.6840663 | R65: =LN(M65) -> 5.0641608 | S65: 0 | T65: Synthetic 2026 | U65: 0.080767648 | V65: 0.090109686 | W65: 0.081036879 | X65: 0.080196263 | Y65: 0.98267779
A66: BP | B66: 46143 | C66: 2026 | D66: 5 | E66: 31 | F66: =Assumptions_2026!$G$2*U66 -> 2.7803242 | G66: =Assumptions_2026!$G$3*V66 -> 0.046002445 | H66: =Annual_Data!$E$6+(Assumptions_2026!$G$4-Annual_Data!$E$6)*D66/12 -> 97.114868 | I66: =Assumptions_2026!$G$5*Y66 -> 2315.1481 | J66: =Assumptions_2026!$G$6*W66 -> 16868.615 | K66: =Assumptions_2026!$G$7*X66 -> 11187.347 | L66: =K66*0.0036 -> 40.274449 | M66: =K66/(I66*E66/1000) -> 155.87865 | N66: =LN(F66) -> 1.0225675 | O66: =LN(G66) -> -3.0790607 | P66: =LN(I66) -> 7.7472289 | Q66: =LN(J66) -> 9.7332101 | R66: =LN(M66) -> 5.0490778 | S66: 0 | T66: Synthetic 2026 | U66: 0.082194467 | V66: 0.089425458 | W66: 0.085118813 | X66: 0.082322272 | Y66: 0.99102446
A67: BP | B67: 46174 | C67: 2026 | D67: 6 | E67: 30 | F67: =Assumptions_2026!$G$2*U67 -> 2.8195062 | G67: =Assumptions_2026!$G$3*V67 -> 0.043542779 | H67: =Annual_Data!$E$6+(Assumptions_2026!$G$4-Annual_Data!$E$6)*D67/12 -> 97.797842 | I67: =Assumptions_2026!$G$5*Y67 -> 2342.5729 | J67: =Assumptions_2026!$G$6*W67 -> 16307.944 | K67: =Assumptions_2026!$G$7*X67 -> 11236.387 | L67: =K67*0.0036 -> 40.450994 | M67: =K67/(I67*E67/1000) -> 159.8867 | N67: =LN(F67) -> 1.0365618 | O67: =LN(G67) -> -3.1340114 | P67: =LN(I67) -> 7.7590051 | Q67: =LN(J67) -> 9.6994076 | R67: =LN(M67) -> 5.0744654 | S67: 0 | T67: Synthetic 2026 | U67: 0.083352801 | V67: 0.084644044 | W67: 0.082289675 | X67: 0.082683137 | Y67: 1.002764
A68: BP | B68: 46204 | C68: 2026 | D68: 7 | E68: 31 | F68: =Assumptions_2026!$G$2*U68 -> 2.9067057 | G68: =Assumptions_2026!$G$3*V68 -> 0.043763749 | H68: =Annual_Data!$E$6+(Assumptions_2026!$G$4-Annual_Data!$E$6)*D68/12 -> 98.480816 | I68: =Assumptions_2026!$G$5*Y68 -> 2346.2771 | J68: =Assumptions_2026!$G$6*W68 -> 16947.863 | K68: =Assumptions_2026!$G$7*X68 -> 11782.078 | L68: =K68*0.0036 -> 42.415481 | M68: =K68/(I68*E68/1000) -> 161.98728 | N68: =LN(F68) -> 1.0670204 | O68: =LN(G68) -> -3.1289495 | P68: =LN(I68) -> 7.7605851 | Q68: =LN(J68) -> 9.7378971 | R68: =LN(M68) -> 5.0875178 | S68: 0 | T68: Synthetic 2026 | U68: 0.085930671 | V68: 0.085073593 | W68: 0.085518701 | X68: 0.086698613 | Y68: 1.0043496
A69: BP | B69: 46235 | C69: 2026 | D69: 8 | E69: 31 | F69: =Assumptions_2026!$G$2*U69 -> 2.8950207 | G69: =Assumptions_2026!$G$3*V69 -> 0.042313325 | H69: =Annual_Data!$E$6+(Assumptions_2026!$G$4-Annual_Data!$E$6)*D69/12 -> 99.163789 | I69: =Assumptions_2026!$G$5*Y69 -> 2346.8488 | J69: =Assumptions_2026!$G$6*W69 -> 16579.618 | K69: =Assumptions_2026!$G$7*X69 -> 11880.838 | L69: =K69*0.0036 -> 42.771015 | M69: =K69/(I69*E69/1000) -> 163.30529 | N69: =LN(F69) -> 1.0629923 | O69: =LN(G69) -> -3.1626532 | P69: =LN(I69) -> 7.7608288 | Q69: =LN(J69) -> 9.7159294 | R69: =LN(M69) -> 5.0956214 | S69: 0 | T69: Synthetic 2026 | U69: 0.08558523 | V69: 0.082254074 | W69: 0.08366054 | X69: 0.087425335 | Y69: 1.0045943
A70: BP | B70: 46266 | C70: 2026 | D70: 9 | E70: 30 | F70: =Assumptions_2026!$G$2*U70 -> 2.7565433 | G70: =Assumptions_2026!$G$3*V70 -> 0.037251185 | H70: =Annual_Data!$E$6+(Assumptions_2026!$G$4-Annual_Data!$E$6)*D70/12 -> 99.846763 | I70: =Assumptions_2026!$G$5*Y70 -> 2349.1106 | J70: =Assumptions_2026!$G$6*W70 -> 17242.968 | K70: =Assumptions_2026!$G$7*X70 -> 10910.76 | L70: =K70*0.0036 -> 39.278734 | M70: =K70/(I70*E70/1000) -> 154.82114 | N70: =LN(F70) -> 1.0139775 | O70: =LN(G70) -> -3.2900715 | P70: =LN(I70) -> 7.7617921 | Q70: =LN(J70) -> 9.7551597 | R70: =LN(M70) -> 5.0422705 | S70: 0 | T70: Synthetic 2026 | U70: 0.081491434 | V70: 0.072413635 | W70: 0.087007795 | X70: 0.080287 | Y70: 1.0055625
A71: BP | B71: 46296 | C71: 2026 | D71: 10 | E71: 31 | F71: =Assumptions_2026!$G$2*U71 -> 2.7902629 | G71: =Assumptions_2026!$G$3*V71 -> 0.03309703 | H71: =Annual_Data!$E$6+(Assumptions_2026!$G$4-Annual_Data!$E$6)*D71/12 -> 100.52974 | I71: =Assumptions_2026!$G$5*Y71 -> 2387.5601 | J71: =Assumptions_2026!$G$6*W71 -> 17587.92 | K71: =Assumptions_2026!$G$7*X71 -> 11300.383 | L71: =K71*0.0036 -> 40.681379 | M71: =K71/(I71*E71/1000) -> 152.67824 | N71: =LN(F71) -> 1.0261358 | O71: =LN(G71) -> -3.4083117 | P71: =LN(I71) -> 7.7780273 | Q71: =LN(J71) -> 9.7749676 | R71: =LN(M71) -> 5.0283327 | S71: 0 | T71: Synthetic 2026 | U71: 0.082488284 | V71: 0.064338256 | W71: 0.088748419 | X71: 0.08315405 | Y71: 1.0220212
A72: BP | B72: 46327 | C72: 2026 | D72: 11 | E72: 30 | F72: =Assumptions_2026!$G$2*U72 -> 2.8015051 | G72: =Assumptions_2026!$G$3*V72 -> 0.031513829 | H72: =Annual_Data!$E$6+(Assumptions_2026!$G$4-Annual_Data!$E$6)*D72/12 -> 101.21271 | I72: =Assumptions_2026!$G$5*Y72 -> 2352.9527 | J72: =Assumptions_2026!$G$6*W72 -> 16651.451 | K72: =Assumptions_2026!$G$7*X72 -> 11239.22 | L72: =K72*0.0036 -> 40.461191 | M72: =K72/(I72*E72/1000) -> 159.2215 | N72: =LN(F72) -> 1.0301568 | O72: =LN(G72) -> -3.4573288 | P72: =LN(I72) -> 7.7634263 | Q72: =LN(J72) -> 9.7202526 | R72: =LN(M72) -> 5.0702963 | S72: 0 | T72: Synthetic 2026 | U72: 0.082820637 | V72: 0.061260627 | W72: 0.084023007 | X72: 0.082703981 | Y72: 1.0072071
A73: BP | B73: 46357 | C73: 2026 | D73: 12 | E73: 31 | F73: =Assumptions_2026!$G$2*U73 -> 2.963588 | G73: =Assumptions_2026!$G$3*V73 -> 0.031905812 | H73: =Annual_Data!$E$6+(Assumptions_2026!$G$4-Annual_Data!$E$6)*D73/12 -> 101.89568 | I73: =Assumptions_2026!$G$5*Y73 -> 2355.0539 | J73: =Assumptions_2026!$G$6*W73 -> 17335.209 | K73: =Assumptions_2026!$G$7*X73 -> 11818.963 | L73: =K73*0.0036 -> 42.548267 | M73: =K73/(I73*E73/1000) -> 161.88881 | N73: =LN(F73) -> 1.0864007 | O73: =LN(G73) -> -3.4449671 | P73: =LN(I73) -> 7.7643189 | Q73: =LN(J73) -> 9.7604949 | R73: =LN(M73) -> 5.0869097 | S73: 0 | T73: Synthetic 2026 | U73: 0.087612278 | V73: 0.062022614 | W73: 0.087473242 | X73: 0.08697003 | Y73: 1.0081066
A74: Chevron | B74: 44197 | C74: 2021 | D74: 1 | E74: 31 | F74: =Annual_Data!$C$7*U74 -> 4.9548683 | G74: =Annual_Data!$D$7*V74 -> 0.19754705 | H74: =(2*Annual_Data!$E$7-Annual_Data!$E$8)+(Annual_Data!$E$7-(2*Annual_Data!$E$7-Annual_Data!$E$8))*D74/12 -> 36.766667 | I74: =Annual_Data!$F$7*Y74 -> 3107.8056 | J74: =Annual_Data!$H$7*W74 -> 10881.22 | K74: =Annual_Data!$I$7*X74 -> 18144.114 | L74: =K74*0.0036 -> 65.318811 | M74: =K74/(I74*E74/1000) -> 188.33031 | N74: =LN(F74) -> 1.6003706 | O74: =LN(G74) -> -1.6217785 | P74: =LN(I74) -> 8.0416722 | Q74: =LN(J74) -> 9.2947936 | R74: =LN(M74) -> 5.2381974 | S74: 0 | T74: Disaggregated (from annual) | U74: 0.086927514 | V74: 0.098773527 | W74: 0.06992802 | X74: 0.088149685 | Y74: 1.0028414
A75: Chevron | B75: 44228 | C75: 2021 | D75: 2 | E75: 28 | F75: =Annual_Data!$C$7*U75 -> 4.5021797 | G75: =Annual_Data!$D$7*V75 -> 0.17520061 | H75: =(2*Annual_Data!$E$7-Annual_Data!$E$8)+(Annual_Data!$E$7-(2*Annual_Data!$E$7-Annual_Data!$E$8))*D75/12 -> 36.833333 | I75: =Annual_Data!$F$7*Y75 -> 3138.2518 | J75: =Annual_Data!$H$7*W75 -> 10122.481 | K75: =Annual_Data!$I$7*X75 -> 16472.611 | L75: =K75*0.0036 -> 59.301398 | M75: =K75/(I75*E75/1000) -> 187.46345 | N75: =LN(F75) -> 1.5045617 | O75: =LN(G75) -> -1.7418236 | P75: =LN(I75) -> 8.0514212 | Q75: =LN(J75) -> 9.222514 | R75: =LN(M75) -> 5.2335839 | S75: 0 | T75: Disaggregated (from annual) | U75: 0.078985608 | V75: 0.087600307 | W75: 0.065051994 | X75: 0.080029007 | Y75: 1.012666
A76: Chevron | B76: 44256 | C76: 2021 | D76: 3 | E76: 31 | F76: =Annual_Data!$C$7*U76 -> 5.0046403 | G76: =Annual_Data!$D$7*V76 -> 0.18722806 | H76: =(2*Annual_Data!$E$7-Annual_Data!$E$8)+(Annual_Data!$E$7-(2*Annual_Data!$E$7-Annual_Data!$E$8))*D76/12 -> 36.9 | I76: =Annual_Data!$F$7*Y76 -> 3163.9499 | J76: =Annual_Data!$H$7*W76 -> 11660.501 | K76: =Annual_Data!$I$7*X76 -> 18099.868 | L76: =K76*0.0036 -> 65.159525 | M76: =K76/(I76*E76/1000) -> 184.53728 | N76: =LN(F76) -> 1.6103655 | O76: =LN(G76) -> -1.6754278 | P76: =LN(I76) -> 8.0595765 | Q76: =LN(J76) -> 9.3639624 | R76: =LN(M76) -> 5.2178515 | S76: 0 | T76: Disaggregated (from annual) | U76: 0.087800707 | V76: 0.093614031 | W76: 0.07493606 | X76: 0.087934724 | Y76: 1.0209583
A77: Chevron | B77: 44287 | C77: 2021 | D77: 4 | E77: 30 | F77: =Annual_Data!$C$7*U77 -> 4.6212384 | G77: =Annual_Data!$D$7*V77 -> 0.17143973 | H77: =(2*Annual_Data!$E$7-Annual_Data!$E$8)+(Annual_Data!$E$7-(2*Annual_Data!$E$7-Annual_Data!$E$8))*D77/12 -> 36.966667 | I77: =Annual_Data!$F$7*Y77 -> 3148.3394 | J77: =Annual_Data!$H$7*W77 -> 10826.889 | K77: =Annual_Data!$I$7*X77 -> 17008.864 | L77: =K77*0.0036 -> 61.231911 | M77: =K77/(I77*E77/1000) -> 180.08292 | N77: =LN(F77) -> 1.5306627 | O77: =LN(G77) -> -1.7635235 | P77: =LN(I77) -> 8.0546304 | Q77: =LN(J77) -> 9.2897881 | R77: =LN(M77) -> 5.1934174 | S77: 0 | T77: Disaggregated (from annual) | U77: 0.081074358 | V77: 0.085719863 | W77: 0.069578868 | X77: 0.082634292 | Y77: 1.0159211
A78: Chevron | B78: 44317 | C78: 2021 | D78: 5 | E78: 31 | F78: =Annual_Data!$C$7*U78 -> 4.7808235 | G78: =Annual_Data!$D$7*V78 -> 0.18060491 | H78: =(2*Annual_Data!$E$7-Annual_Data!$E$8)+(Annual_Data!$E$7-(2*Annual_Data!$E$7-Annual_Data!$E$8))*D78/12 -> 37.033333 | I78: =Annual_Data!$F$7*Y78 -> 3124.0332 | J78: =Annual_Data!$H$7*W78 -> 12245.714 | K78: =Annual_Data!$I$7*X78 -> 17486.269 | L78: =K78*0.0036 -> 62.950567 | M78: =K78/(I78*E78/1000) -> 180.55928 | N78: =LN(F78) -> 1.5646128 | O78: =LN(G78) -> -1.7114434 | P78: =LN(I78) -> 8.0468801 | Q78: =LN(J78) -> 9.4129313 | R78: =LN(M78) -> 5.1960591 | S78: 0 | T78: Disaggregated (from annual) | U78: 0.083874096 | V78: 0.090302457 | W78: 0.078696929 | X78: 0.084953669 | Y78: 1.0080778
A79: Chevron | B79: 44348 | C79: 2021 | D79: 6 | E79: 30 | F79: =Annual_Data!$C$7*U79 -> 4.6382097 | G79: =Annual_Data!$D$7*V79 -> 0.17370448 | H79: =(2*Annual_Data!$E$7-Annual_Data!$E$8)+(Annual_Data!$E$7-(2*Annual_Data!$E$7-Annual_Data!$E$8))*D79/12 -> 37.1 | I79: =Annual_Data!$F$7*Y79 -> 3083.2422 | J79: =Annual_Data!$H$7*W79 -> 12088.788 | K79: =Annual_Data!$I$7*X79 -> 16765.127 | L79: =K79*0.0036 -> 60.354457 | M79: =K79/(I79*E79/1000) -> 181.24997 | N79: =LN(F79) -> 1.5343284 | O79: =LN(G79) -> -1.7503998 | P79: =LN(I79) -> 8.033737 | Q79: =LN(J79) -> 9.4000337 | R79: =LN(M79) -> 5.1998771 | S79: 0 | T79: Disaggregated (from annual) | U79: 0.081372099 | V79: 0.086852239 | W79: 0.077688444 | X79: 0.081450142 | Y79: 0.99491521
A80: Chevron | B80: 44378 | C80: 2021 | D80: 7 | E80: 31 | F80: =Annual_Data!$C$7*U80 -> 4.8465259 | G80: =Annual_Data!$D$7*V80 -> 0.17992163 | H80: =(2*Annual_Data!$E$7-Annual_Data!$E$8)+(Annual_Data!$E$7-(2*Annual_Data!$E$7-Annual_Data!$E$8))*D80/12 -> 37.166667 | I80: =Annual_Data!$F$7*Y80 -> 3063.8711 | J80: =Annual_Data!$H$7*W80 -> 13088.31 | K80: =Annual_Data!$I$7*X80 -> 17526.696 | L80: =K80*0.0036 -> 63.096107 | M80: =K80/(I80*E80/1000) -> 184.53038 | N80: =LN(F80) -> 1.5782621 | O80: =LN(G80) -> -1.7152339 | P80: =LN(I80) -> 8.0274345 | Q80: =LN(J80) -> 9.4794748 | R80: =LN(M80) -> 5.2178141 | S80: 0 | T80: Disaggregated (from annual) | U80: 0.08502677 | V80: 0.089960815 | W80: 0.08411186 | X80: 0.08515008 | Y80: 0.98866445
A81: Chevron | B81: 44409 | C81: 2021 | D81: 8 | E81: 31 | F81: =Annual_Data!$C$7*U81 -> 4.8635676 | G81: =Annual_Data!$D$7*V81 -> 0.16976189 | H81: =(2*Annual_Data!$E$7-Annual_Data!$E$8)+(Annual_Data!$E$7-(2*Annual_Data!$E$7-Annual_Data!$E$8))*D81/12 -> 37.233333 | I81: =Annual_Data!$F$7*Y81 -> 3032.9157 | J81: =Annual_Data!$H$7*W81 -> 13222.392 | K81: =Annual_Data!$I$7*X81 -> 17209.195 | L81: =K81*0.0036 -> 61.953104 | M81: =K81/(I81*E81/1000) -> 183.03685 | N81: =LN(F81) -> 1.5817722 | O81: =LN(G81) -> -1.7733585 | P81: =LN(I81) -> 8.0172797 | Q81: =LN(J81) -> 9.489667 | R81: =LN(M81) -> 5.2096875 | S81: 0 | T81: Disaggregated (from annual) | U81: 0.085325748 | V81: 0.084880944 | W81: 0.084973534 | X81: 0.083607563 | Y81: 0.97867559
A82: Chevron | B82: 44440 | C82: 2021 | D82: 9 | E82: 30 | F82: =Annual_Data!$C$7*U82 -> 4.5944026 | G82: =Annual_Data!$D$7*V82 -> 0.15160045 | H82: =(2*Annual_Data!$E$7-Annual_Data!$E$8)+(Annual_Data!$E$7-(2*Annual_Data!$E$7-Annual_Data!$E$8))*D82/12 -> 37.3 | I82: =Annual_Data!$F$7*Y82 -> 3107.5099 | J82: =Annual_Data!$H$7*W82 -> 13597.86 | K82: =Annual_Data!$I$7*X82 -> 16506.913 | L82: =K82*0.0036 -> 59.424885 | M82: =K82/(I82*E82/1000) -> 177.06474 | N82: =LN(F82) -> 1.5248387 | O82: =LN(G82) -> -1.8865068 | P82: =LN(I82) -> 8.041577 | Q82: =LN(J82) -> 9.5176677 | R82: =LN(M82) -> 5.1765154 | S82: 0 | T82: Disaggregated (from annual) | U82: 0.080603554 | V82: 0.075800226 | W82: 0.087386478 | X82: 0.080195656 | Y82: 1.002746
A83: Chevron | B83: 44470 | C83: 2021 | D83: 10 | E83: 31 | F83: =Annual_Data!$C$7*U83 -> 4.6615112 | G83: =Annual_Data!$D$7*V83 -> 0.1465805 | H83: =(2*Annual_Data!$E$7-Annual_Data!$E$8)+(Annual_Data!$E$7-(2*Annual_Data!$E$7-Annual_Data!$E$8))*D83/12 -> 37.366667 | I83: =Annual_Data!$F$7*Y83 -> 3087.5308 | J83: =Annual_Data!$H$7*W83 -> 15450.124 | K83: =Annual_Data!$I$7*X83 -> 16650.883 | L83: =K83*0.0036 -> 59.943179 | M83: =K83/(I83*E83/1000) -> 173.96596 | N83: =LN(F83) -> 1.5393397 | O83: =LN(G83) -> -1.9201805 | P83: =LN(I83) -> 8.0351269 | Q83: =LN(J83) -> 9.6453723 | R83: =LN(M83) -> 5.1588597 | S83: 0 | T83: Disaggregated (from annual) | U83: 0.081780897 | V83: 0.073290251 | W83: 0.099290028 | X83: 0.08089511 | Y83: 0.99629905
A84: Chevron | B84: 44501 | C84: 2021 | D84: 11 | E84: 30 | F84: =Annual_Data!$C$7*U84 -> 4.6925071 | G84: =Annual_Data!$D$7*V84 -> 0.13603985 | H84: =(2*Annual_Data!$E$7-Annual_Data!$E$8)+(Annual_Data!$E$7-(2*Annual_Data!$E$7-Annual_Data!$E$8))*D84/12 -> 37.433333 | I84: =Annual_Data!$F$7*Y84 -> 3078.4631 | J84: =Annual_Data!$H$7*W84 -> 15224.092 | K84: =Annual_Data!$I$7*X84 -> 16672.994 | L84: =K84*0.0036 -> 60.02278 | M84: =K84/(I84*E84/1000) -> 180.53375 | N84: =LN(F84) -> 1.545967 | O84: =LN(G84) -> -1.9948074 | P84: =LN(I84) -> 8.0321858 | Q84: =LN(J84) -> 9.6306345 | R84: =LN(M84) -> 5.1959177 | S84: 0 | T84: Disaggregated (from annual) | U84: 0.082324687 | V84: 0.068019923 | W84: 0.097837436 | X84: 0.081002533 | Y84: 0.99337307
A85: Chevron | B85: 44531 | C85: 2021 | D85: 12 | E85: 31 | F85: =Annual_Data!$C$7*U85 -> 4.8395258 | G85: =Annual_Data!$D$7*V85 -> 0.13037084 | H85: =(2*Annual_Data!$E$7-Annual_Data!$E$8)+(Annual_Data!$E$7-(2*Annual_Data!$E$7-Annual_Data!$E$8))*D85/12 -> 37.5 | I85: =Annual_Data!$F$7*Y85 -> 3056.5812 | J85: =Annual_Data!$H$7*W85 -> 17197.629 | K85: =Annual_Data!$I$7*X85 -> 17289.466 | L85: =K85*0.0036 -> 62.242076 | M85: =K85/(I85*E85/1000) -> 182.46683 | N85: =LN(F85) -> 1.5768167 | O85: =LN(G85) -> -2.0373723 | P85: =LN(I85) -> 8.0250523 | Q85: =LN(J85) -> 9.7525268 | R85: =LN(M85) -> 5.2065684 | S85: 0 | T85: Disaggregated (from annual) | U85: 0.084903961 | V85: 0.065185418 | W85: 0.11052035 | X85: 0.083997539 | Y85: 0.98631212
A86: Chevron | B86: 44562 | C86: 2022 | D86: 1 | E86: 31 | F86: =Annual_Data!$C$8*U86 -> 4.6928102 | G86: =Annual_Data!$D$8*V86 -> 0.12920926 | H86: =Annual_Data!$E$7+(Annual_Data!$E$8-Annual_Data!$E$7)*D86/12 -> 37.566667 | I86: =Annual_Data!$F$8*Y86 -> 3022.8868 | J86: =Annual_Data!$H$8*W86 -> 17522.772 | K86: =Annual_Data!$I$8*X86 -> 16619.101 | L86: =K86*0.0036 -> 59.828765 | M86: =K86/(I86*E86/1000) -> 177.34705 | N86: =LN(F86) -> 1.5460316 | O86: =LN(G86) -> -2.046322 | P86: =LN(I86) -> 8.0139675 | Q86: =LN(J86) -> 9.7712566 | R86: =LN(M86) -> 5.1781085 | S86: 0 | T86: Disaggregated (from annual) | U86: 0.088543589 | V86: 0.12920926 | W86: 0.074338178 | X86: 0.090239301 | Y86: 1.0079649
A87: Chevron | B87: 44593 | C87: 2022 | D87: 2 | E87: 28 | F87: =Annual_Data!$C$8*U87 -> 4.2310346 | G87: =Annual_Data!$D$8*V87 -> 0.10127113 | H87: =Annual_Data!$E$7+(Annual_Data!$E$8-Annual_Data!$E$7)*D87/12 -> 37.633333 | I87: =Annual_Data!$F$8*Y87 -> 3009.2036 | J87: =Annual_Data!$H$8*W87 -> 16610.495 | K87: =Annual_Data!$I$8*X87 -> 14645.29 | L87: =K87*0.0036 -> 52.723044 | M87: =K87/(I87*E87/1000) -> 173.81545 | N87: =LN(F87) -> 1.4424466 | O87: =LN(G87) -> -2.2899539 | P87: =LN(I87) -> 8.0094307 | Q87: =LN(J87) -> 9.71779 | R87: =LN(M87) -> 5.1579941 | S87: 0 | T87: Disaggregated (from annual) | U87: 0.079830842 | V87: 0.10127113 | W87: 0.070467957 | X87: 0.079521792 | Y87: 1.0034023
A88: Chevron | B88: 44621 | C88: 2022 | D88: 3 | E88: 31 | F88: =Annual_Data!$C$8*U88 -> 4.6065435 | G88: =Annual_Data!$D$8*V88 -> 0.099808939 | H88: =Annual_Data!$E$7+(Annual_Data!$E$8-Annual_Data!$E$7)*D88/12 -> 37.7 | I88: =Annual_Data!$F$8*Y88 -> 2990.9015 | J88: =Annual_Data!$H$8*W88 -> 19564.612 | K88: =Annual_Data!$I$8*X88 -> 15914.025 | L88: =K88*0.0036 -> 57.290488 | M88: =K88/(I88*E88/1000) -> 171.6391 | N88: =LN(F88) -> 1.5274778 | O88: =LN(G88) -> -2.3044975 | P88: =LN(I88) -> 8.0033301 | Q88: =LN(J88) -> 9.8814777 | R88: =LN(M88) -> 5.145394 | S88: 0 | T88: Disaggregated (from annual) | U88: 0.086915916 | V88: 0.099808939 | W88: 0.083000427 | X88: 0.086410837 | Y88: 0.9972996
A89: Chevron | B89: 44652 | C89: 2022 | D89: 4 | E89: 30 | F89: =Annual_Data!$C$8*U89 -> 4.2820767 | G89: =Annual_Data!$D$8*V89 -> 0.090962219 | H89: =Annual_Data!$E$7+(Annual_Data!$E$8-Annual_Data!$E$7)*D89/12 -> 37.766667 | I89: =Annual_Data!$F$8*Y89 -> 2987.7413 | J89: =Annual_Data!$H$8*W89 -> 19747.488 | K89: =Annual_Data!$I$8*X89 -> 14950.451 | L89: =K89*0.0036 -> 53.821623 | M89: =K89/(I89*E89/1000) -> 166.7977 | N89: =LN(F89) -> 1.4544381 | O89: =LN(G89) -> -2.397311 | P89: =LN(I89) -> 8.002273 | Q89: =LN(J89) -> 9.8907816 | R89: =LN(M89) -> 5.1167817 | S89: 0 | T89: Disaggregated (from annual) | U89: 0.080793901 | V89: 0.090962219 | W89: 0.083776256 | X89: 0.081178771 | Y89: 0.99624584
A90: Chevron | B90: 44682 | C90: 2022 | D90: 5 | E90: 31 | F90: =Annual_Data!$C$8*U90 -> 4.4118081 | G90: =Annual_Data!$D$8*V90 -> 0.088017947 | H90: =Annual_Data!$E$7+(Annual_Data!$E$8-Annual_Data!$E$7)*D90/12 -> 37.833333 | I90: =Annual_Data!$F$8*Y90 -> 2995.551 | J90: =Annual_Data!$H$8*W90 -> 20475.824 | K90: =Annual_Data!$I$8*X90 -> 15277.363 | L90: =K90*0.0036 -> 54.998506 | M90: =K90/(I90*E90/1000) -> 164.5167 | N90: =LN(F90) -> 1.4842846 | O90: =LN(G90) -> -2.4302145 | P90: =LN(I90) -> 8.0048835 | Q90: =LN(J90) -> 9.9270001 | R90: =LN(M90) -> 5.1030121 | S90: 0 | T90: Disaggregated (from annual) | U90: 0.083241663 | V90: 0.088017947 | W90: 0.086866131 | X90: 0.082953856 | Y90: 0.99884996
A91: Chevron | B91: 44713 | C91: 2022 | D91: 6 | E91: 30 | F91: =Annual_Data!$C$8*U91 -> 4.3156443 | G91: =Annual_Data!$D$8*V91 -> 0.078662357 | H91: =Annual_Data!$E$7+(Annual_Data!$E$8-Annual_Data!$E$7)*D91/12 -> 37.9 | I91: =Annual_Data!$F$8*Y91 -> 2992.7607 | J91: =Annual_Data!$H$8*W91 -> 20153.332 | K91: =Annual_Data!$I$8*X91 -> 14991.763 | L91: =K91*0.0036 -> 53.970346 | M91: =K91/(I91*E91/1000) -> 166.97808 | N91: =LN(F91) -> 1.4622466 | O91: =LN(G91) -> -2.5425906 | P91: =LN(I91) -> 8.0039516 | Q91: =LN(J91) -> 9.9111249 | R91: =LN(M91) -> 5.1178625 | S91: 0 | T91: Disaggregated (from annual) | U91: 0.081427251 | V91: 0.078662357 | W91: 0.085498001 | X91: 0.081403089 | Y91: 0.99791954
A92: Chevron | B92: 44743 | C92: 2022 | D92: 7 | E92: 31 | F92: =Annual_Data!$C$8*U92 -> 4.5793137 | G92: =Annual_Data!$D$8*V92 -> 0.079659049 | H92: =Annual_Data!$E$7+(Annual_Data!$E$8-Annual_Data!$E$7)*D92/12 -> 37.966667 | I92: =Annual_Data!$F$8*Y92 -> 3007.8094 | J92: =Annual_Data!$H$8*W92 -> 20368.247 | K92: =Annual_Data!$I$8*X92 -> 15774.718 | L92: =K92*0.0036 -> 56.788986 | M92: =K92/(I92*E92/1000) -> 169.18023 | N92: =LN(F92) -> 1.5215491 | O92: =LN(G92) -> -2.5299996 | P92: =LN(I92) -> 8.0089673 | Q92: =LN(J92) -> 9.9217324 | R92: =LN(M92) -> 5.1309646 | S92: 0 | T92: Disaggregated (from annual) | U92: 0.086402146 | V92: 0.079659049 | W92: 0.08640975 | X92: 0.085654424 | Y92: 1.0029374
A93: Chevron | B93: 44774 | C93: 2022 | D93: 8 | E93: 31 | F93: =Annual_Data!$C$8*U93 -> 4.49734 | G93: =Annual_Data!$D$8*V93 -> 0.073354544 | H93: =Annual_Data!$E$7+(Annual_Data!$E$8-Annual_Data!$E$7)*D93/12 -> 38.033333 | I93: =Annual_Data!$F$8*Y93 -> 2981.6497 | J93: =Annual_Data!$H$8*W93 -> 21337.942 | K93: =Annual_Data!$I$8*X93 -> 15477.064 | L93: =K93*0.0036 -> 55.717429 | M93: =K93/(I93*E93/1000) -> 167.44426 | N93: =LN(F93) -> 1.5034861 | O93: =LN(G93) -> -2.6124508 | P93: =LN(I93) -> 8.000232 | Q93: =LN(J93) -> 9.9682421 | R93: =LN(M93) -> 5.1206505 | S93: 0 | T93: Disaggregated (from annual) | U93: 0.084855472 | V93: 0.073354544 | W93: 0.090523559 | X93: 0.084038203 | Y93: 0.99421464
A94: Chevron | B94: 44805 | C94: 2022 | D94: 9 | E94: 30 | F94: =Annual_Data!$C$8*U94 -> 4.1977457 | G94: =Annual_Data!$D$8*V94 -> 0.067638184 | H94: =Annual_Data!$E$7+(Annual_Data!$E$8-Annual_Data!$E$7)*D94/12 -> 38.1 | I94: =Annual_Data!$F$8*Y94 -> 2953.8766 | J94: =Annual_Data!$H$8*W94 -> 20123.352 | K94: =Annual_Data!$I$8*X94 -> 14576.147 | L94: =K94*0.0036 -> 52.474129 | M94: =K94/(I94*E94/1000) -> 164.48607 | N94: =LN(F94) -> 1.4345476 | O94: =LN(G94) -> -2.6935826 | P94: =LN(I94) -> 7.9908737 | Q94: =LN(J94) -> 9.9096362 | R94: =LN(M94) -> 5.1028259 | S94: 0 | T94: Disaggregated (from annual) | U94: 0.079202749 | V94: 0.067638184 | W94: 0.085370815 | X94: 0.079146357 | Y94: 0.98495385
A95: Chevron | B95: 44835 | C95: 2022 | D95: 10 | E95: 31 | F95: =Annual_Data!$C$8*U95 -> 4.3155916 | G95: =Annual_Data!$D$8*V95 -> 0.064567077 | H95: =Annual_Data!$E$7+(Annual_Data!$E$8-Annual_Data!$E$7)*D95/12 -> 38.166667 | I95: =Annual_Data!$F$8*Y95 -> 2990.6252 | J95: =Annual_Data!$H$8*W95 -> 20514.285 | K95: =Annual_Data!$I$8*X95 -> 14938.476 | L95: =K95*0.0036 -> 53.778514 | M95: =K95/(I95*E95/1000) -> 161.1323 | N95: =LN(F95) -> 1.4622344 | O95: =LN(G95) -> -2.7400506 | P95: =LN(I95) -> 8.0032377 | Q95: =LN(J95) -> 9.9288767 | R95: =LN(M95) -> 5.0822258 | S95: 0 | T95: Disaggregated (from annual) | U95: 0.081426257 | V95: 0.064567077 | W95: 0.087029297 | X95: 0.08111375 | Y95: 0.99720747
A96: Chevron | B96: 44866 | C96: 2022 | D96: 11 | E96: 30 | F96: =Annual_Data!$C$8*U96 -> 4.3449001 | G96: =Annual_Data!$D$8*V96 -> 0.059913001 | H96: =Annual_Data!$E$7+(Annual_Data!$E$8-Annual_Data!$E$7)*D96/12 -> 38.233333 | I96: =Annual_Data!$F$8*Y96 -> 3026.2096 | J96: =Annual_Data!$H$8*W96 -> 20343.562 | K96: =Annual_Data!$I$8*X96 -> 15315.234 | L96: =K96*0.0036 -> 55.134843 | M96: =K96/(I96*E96/1000) -> 168.69546 | N96: =LN(F96) -> 1.4690028 | O96: =LN(G96) -> -2.8148618 | P96: =LN(I96) -> 8.0150662 | Q96: =LN(J96) -> 9.9205198 | R96: =LN(M96) -> 5.1280951 | S96: 0 | T96: Disaggregated (from annual) | U96: 0.081979247 | V96: 0.059913001 | W96: 0.086305028 | X96: 0.083159492 | Y96: 1.0090729
A97: Chevron | B97: 44896 | C97: 2022 | D97: 12 | E97: 31 | F97: =Annual_Data!$C$8*U97 -> 4.5251913 | G97: =Annual_Data!$D$8*V97 -> 0.066936291 | H97: =Annual_Data!$E$7+(Annual_Data!$E$8-Annual_Data!$E$7)*D97/12 -> 38.3 | I97: =Annual_Data!$F$8*Y97 -> 3028.6297 | J97: =Annual_Data!$H$8*W97 -> 18955.089 | K97: =Annual_Data!$I$8*X97 -> 15687.369 | L97: =K97*0.0036 -> 56.474527 | M97: =K97/(I97*E97/1000) -> 167.08683 | N97: =LN(F97) -> 1.5096598 | O97: =LN(G97) -> -2.704014 | P97: =LN(I97) -> 8.0158656 | Q97: =LN(J97) -> 9.8498277 | R97: =LN(M97) -> 5.1185136 | S97: 0 | T97: Disaggregated (from annual) | U97: 0.085380968 | V97: 0.066936291 | W97: 0.080414602 | X97: 0.085180127 | Y97: 1.0098799
A98: Chevron | B98: 44927 | C98: 2023 | D98: 1 | E98: 31 | F98: =Annual_Data!$C$9*U98 -> 4.5218068 | G98: =Annual_Data!$D$9*V98 -> 0.066730656 | H98: =Annual_Data!$E$8+(Annual_Data!$E$9-Annual_Data!$E$8)*D98/12 -> 38.458333 | I98: =Annual_Data!$F$9*Y98 -> 3034.1755 | J98: =Annual_Data!$H$9*W98 -> 18547.451 | K98: =Annual_Data!$I$9*X98 -> 15792.179 | L98: =K98*0.0036 -> 56.851843 | M98: =K98/(I98*E98/1000) -> 167.89573 | N98: =LN(F98) -> 1.5089117 | O98: =LN(G98) -> -2.7070908 | P98: =LN(I98) -> 8.017695 | Q98: =LN(J98) -> 9.8280877 | R98: =LN(M98) -> 5.1233432 | S98: 0 | T98: Disaggregated (from annual) | U98: 0.086957824 | V98: 0.066730656 | W98: 0.094191097 | X98: 0.085235045 | Y98: 0.97249215
A99: Chevron | B99: 44958 | C99: 2023 | D99: 2 | E99: 28 | F99: =Annual_Data!$C$9*U99 -> 4.0158939 | G99: =Annual_Data!$D$9*V99 -> 0.058360948 | H99: =Annual_Data!$E$8+(Annual_Data!$E$9-Annual_Data!$E$8)*D99/12 -> 38.616667 | I99: =Annual_Data!$F$9*Y99 -> 3054.9674 | J99: =Annual_Data!$H$9*W99 -> 16428.928 | K99: =Annual_Data!$I$9*X99 -> 14210.144 | L99: =K99*0.0036 -> 51.156519 | M99: =K99/(I99*E99/1000) -> 166.12457 | N99: =LN(F99) -> 1.39026 | O99: =LN(G99) -> -2.8411083 | P99: =LN(I99) -> 8.0245242 | Q99: =LN(J99) -> 9.706799 | R99: =LN(M99) -> 5.1127379 | S99: 0 | T99: Disaggregated (from annual) | U99: 0.07722873 | V99: 0.058360948 | W99: 0.08343242 | X99: 0.076696338 | Y99: 0.97915621
A100: Chevron | B100: 44986 | C100: 2023 | D100: 3 | E100: 31 | F100: =Annual_Data!$C$9*U100 -> 4.4471514 | G100: =Annual_Data!$D$9*V100 -> 0.065761031 | H100: =Annual_Data!$E$8+(Annual_Data!$E$9-Annual_Data!$E$8)*D100/12 -> 38.775 | I100: =Annual_Data!$F$9*Y100 -> 3045.367 | J100: =Annual_Data!$H$9*W100 -> 17557.926 | K100: =Annual_Data!$I$9*X100 -> 15777.82 | L100: =K100*0.0036 -> 56.800154 | M100: =K100/(I100*E100/1000) -> 167.12664 | N100: =LN(F100) -> 1.4922638 | O100: =LN(G100) -> -2.7217278 | P100: =LN(I100) -> 8.0213767 | Q100: =LN(J100) -> 9.7732608 | R100: =LN(M100) -> 5.1187518 | S100: 0 | T100: Disaggregated (from annual) | U100: 0.085522143 | V100: 0.065761031 | W100: 0.089165906 | X100: 0.085157549 | Y100: 0.97607916
...

Sheet Assumptions_2026
A1: company | B1: variable | C1: value_2021 | D1: value_2025 | E1: cagr_2021_25 | F1: growth_used_2026 | G1: target_2026 | H1: basis_for_growth_used
A2: BP | B2: scope1_mt_co2e | C2: =Annual_Data!C2 -> 33.2 | D2: =Annual_Data!C6 -> 33.7 | E2: =(D2/C2)^(1/4)-1 -> 0.0037439816 | F2: =E2 -> 0.0037439816 | G2: =D2*(1+F2) -> 33.826172 | H2: 2021-2025 CAGR (default)
A3: BP | B3: scope2_location_mt_co2e | C3: =Annual_Data!D2 -> 2.4 | D3: =Annual_Data!D6 -> 0.7 | E3: =(D3/C3)^(1/4)-1 -> -0.26511108 | F3: =E3 -> -0.26511108 | G3: =D3*(1+F3) -> 0.51442224 | H3: 2021-2025 CAGR (default)
A4: BP | B4: employees_000 | C4: =Annual_Data!E2 -> 67 | D4: =Annual_Data!E6 -> 93.7 | E4: =(D4/C4)^(1/4)-1 -> 0.087467276 | F4: =E4 -> 0.087467276 | G4: =D4*(1+F4) -> 101.89568 | H4: 2021-2025 CAGR (default)
A5: BP | B5: production_koebd_P | C5: =Annual_Data!F2 -> 2218 | D5: =Annual_Data!F6 -> 2312 | E5: =(D5/C5)^(1/4)-1 -> 0.010430791 | F5: =E5 -> 0.010430791 | G5: =D5*(1+F5) -> 2336.116 | H5: 2021-2025 CAGR (default)
A6: BP | B6: revenue_usd_millions_A | C6: =Annual_Data!H2 -> 157739 | D6: =Annual_Data!H6 -> 189335 | E6: =(D6/C6)^(1/4)-1 -> 0.046701762 | F6: =E6 -> 0.046701762 | G6: =D6*(1+F6) -> 198177.28 | H6: 2021-2025 CAGR (default)
A7: BP | B7: total_energy_consumption_GWh | C7: =Annual_Data!I2 -> 128805 | D7: =Annual_Data!I6 -> 134448 | E7: =(D7/C7)^(1/4)-1 -> 0.010777128 | F7: =E7 -> 0.010777128 | G7: =D7*(1+F7) -> 135896.96 | H7: 2021-2025 CAGR (default)
A8: Chevron | B8: scope1_mt_co2e | C8: =Annual_Data!C7 -> 57 | D8: =Annual_Data!C11 -> 55 | E8: =(D8/C8)^(1/4)-1 -> -0.0088897709 | F8: =E8 -> -0.0088897709 | G8: =D8*(1+F8) -> 54.511063 | H8: 2021-2025 CAGR (default)
A9: Chevron | B9: scope2_location_mt_co2e | C9: =Annual_Data!D7 -> 2 | D9: =Annual_Data!D11 -> 2 | E9: =(D9/C9)^(1/4)-1 -> 0 | F9: =E9 -> 0 | G9: =D9*(1+F9) -> 2 | H9: 2021-2025 CAGR (default)
A10: Chevron | B10: employees_000 | C10: =Annual_Data!E7 -> 37.5 | D10: =Annual_Data!E11 -> 43 | E10: =(D10/C10)^(1/4)-1 -> 0.034806855 | F10: =E10 -> 0.034806855 | G10: =D10*(1+F10) -> 44.496695 | H10: 2021-2025 CAGR (default)
A11: Chevron | B11: production_koebd_P | C11: =Annual_Data!F7 -> 3099 | D11: =Annual_Data!F11 -> 3723 | E11: =(D11/C11)^(1/4)-1 -> 0.046930531 | F11: 0.085146 | G11: =D11*(1+F11) -> 4039.9986 | H11: Company guidance: 2026 production 3,980-4,100 kboe/d (midpoint 4,040), Q4 2025 results
A12: Chevron | B12: revenue_usd_millions_A | C12: =Annual_Data!H7 -> 155606 | D12: =Annual_Data!H11 -> 184432 | E12: =(D12/C12)^(1/4)-1 -> 0.043403969 | F12: =E12 -> 0.043403969 | G12: =D12*(1+F12) -> 192437.08 | H12: 2021-2025 CAGR (default)
A13: Chevron | B13: total_energy_consumption_GWh | C13: =Annual_Data!I7 -> 205833 | D13: =Annual_Data!I11 -> 197778 | E13: =(D13/C13)^(1/4)-1 -> -0.0099303578 | F13: =E13 -> -0.0099303578 | G13: =D13*(1+F13) -> 195813.99 | H13: 2021-2025 CAGR (default)
A14: ConocoPhillips | B14: scope1_mt_co2e | C14: =Annual_Data!C12 -> 17.7 | D14: =Annual_Data!C16 -> 18.4 | E14: =(D14/C14)^(1/4)-1 -> 0.0097436697 | F14: =E14 -> 0.0097436697 | G14: =D14*(1+F14) -> 18.579284 | H14: 2021-2025 CAGR (default)
A15: ConocoPhillips | B15: scope2_location_mt_co2e | C15: =Annual_Data!D12 -> 1.03 | D15: =Annual_Data!D16 -> 1.18 | E15: =(D15/C15)^(1/4)-1 -> 0.034573132 | F15: =E15 -> 0.034573132 | G15: =D15*(1+F15) -> 1.2207963 | H15: 2021-2025 CAGR (default)
A16: ConocoPhillips | B16: employees_000 | C16: =Annual_Data!E12 -> 10.4 | D16: =Annual_Data!E16 -> 12 | E16: =(D16/C16)^(1/4)-1 -> 0.036422844 | F16: =E16 -> 0.036422844 | G16: =D16*(1+F16) -> 12.437074 | H16: 2021-2025 CAGR (default)
A17: ConocoPhillips | B17: production_koebd_P | C17: =Annual_Data!F12 -> 1901 | D17: =Annual_Data!F16 -> 2742 | E17: =(D17/C17)^(1/4)-1 -> 0.095901026 | F17: =E17 -> 0.095901026 | G17: =D17*(1+F17) -> 3004.9606 | H17: 2021-2025 CAGR (default)
A18: ConocoPhillips | B18: revenue_usd_millions_A | C18: =Annual_Data!H12 -> 45828 | D18: =Annual_Data!H16 -> 58944 | E18: =(D18/C18)^(1/4)-1 -> 0.06494499 | F18: =E18 -> 0.06494499 | G18: =D18*(1+F18) -> 62772.118 | H18: 2021-2025 CAGR (default)
A19: ConocoPhillips | B19: total_energy_consumption_GWh | C19: =Annual_Data!I12 -> 63596 | D19: =Annual_Data!I16 -> 72682 | E19: =(D19/C19)^(1/4)-1 -> 0.033949356 | F19: =E19 -> 0.033949356 | G19: =D19*(1+F19) -> 75149.507 | H19: 2021-2025 CAGR (default)
A20: Equinor | B20: scope1_mt_co2e | C20: =Annual_Data!C17 -> 12.01 | D20: =Annual_Data!C21 -> 10.04 | E20: =(D20/C20)^(1/4)-1 -> -0.04380234 | F20: =E20 -> -0.04380234 | G20: =D20*(1+F20) -> 9.6002245 | H20: 2021-2025 CAGR (default)
A21: Equinor | B21: scope2_location_mt_co2e | C21: =Annual_Data!D17 -> 0.1 | D21: =Annual_Data!D21 -> 0.05 | E21: =(D21/C21)^(1/4)-1 -> -0.15910358 | F21: =E21 -> -0.15910358 | G21: =D21*(1+F21) -> 0.042044821 | H21: 2021-2025 CAGR (default)
A22: Equinor | B22: employees_000 | C22: =Annual_Data!E17 -> 21.126 | D22: =Annual_Data!E21 -> 24.6 | E22: =(D22/C22)^(1/4)-1 -> 0.038794061 | F22: =E22 -> 0.038794061 | G22: =D22*(1+F22) -> 25.554334 | H22: 2021-2025 CAGR (default)
A23: Equinor | B23: production_koebd_P | C23: =Annual_Data!F17 -> 2079 | D23: =Annual_Data!F21 -> 2137 | E23: =(D23/C23)^(1/4)-1 -> 0.0069027065 | F23: 0.03 | G23: =D23*(1+F23) -> 2201.11 | H23: Company guidance: ~3% oil & gas production growth in 2026, Q4 2025 report
A24: Equinor | B24: revenue_usd_millions_A | C24: =Annual_Data!H17 -> 88744 | D24: =Annual_Data!H21 -> 105828 | E24: =(D24/C24)^(1/4)-1 -> 0.044997851 | F24: =E24 -> 0.044997851 | G24: =D24*(1+F24) -> 110590.03 | H24: 2021-2025 CAGR (default)
A25: Equinor | B25: total_energy_consumption_GWh | C25: =Annual_Data!I17 -> 59000 | D25: =Annual_Data!I21 -> 49000 | E25: =(D25/C25)^(1/4)-1 -> -0.045367936 | F25: =E25 -> -0.045367936 | G25: =D25*(1+F25) -> 46776.971 | H25: 2021-2025 CAGR (default)
A26: ExxonMobil | B26: scope1_mt_co2e | C26: =Annual_Data!C22 -> 98 | D26: =Annual_Data!C26 -> 90 | E26: =(D26/C26)^(1/4)-1 -> -0.021064431 | F26: =E26 -> -0.021064431 | G26: =D26*(1+F26) -> 88.104201 | H26: 2021-2025 CAGR (default)
A27: ExxonMobil | B27: scope2_location_mt_co2e | C27: =Annual_Data!D22 -> 7 | D27: =Annual_Data!D26 -> 9 | E27: =(D27/C27)^(1/4)-1 -> 0.064844317 | F27: =E27 -> 0.064844317 | G27: =D27*(1+F27) -> 9.5835989 | H27: 2021-2025 CAGR (default)
A28: ExxonMobil | B28: employees_000 | C28: =Annual_Data!E22 -> 62 | D28: =Annual_Data!E26 -> 58 | E28: =(D28/C28)^(1/4)-1 -> -0.016534621 | F28: =E28 -> -0.016534621 | G28: =D28*(1+F28) -> 57.040992 | H28: 2021-2025 CAGR (default)
A29: ExxonMobil | B29: production_koebd_P | C29: =Annual_Data!F22 -> 3712 | D29: =Annual_Data!F26 -> 4736 | E29: =(D29/C29)^(1/4)-1 -> 0.062798497 | F29: =E29 -> 0.062798497 | G29: =D29*(1+F29) -> 5033.4137 | H29: 2021-2025 CAGR (default)
A30: ExxonMobil | B30: revenue_usd_millions_A | C30: =Annual_Data!H22 -> 276692 | D30: =Annual_Data!H26 -> 323905 | E30: =(D30/C30)^(1/4)-1 -> 0.040172248 | F30: =E30 -> 0.040172248 | G30: =D30*(1+F30) -> 336916.99 | H30: 2021-2025 CAGR (default)
A31: ExxonMobil | B31: total_energy_consumption_GWh | C31: =Annual_Data!I22 -> 416667 | D31: =Annual_Data!I26 -> 388889 | E31: =(D31/C31)^(1/4)-1 -> -0.017100445 | F31: =E31 -> -0.017100445 | G31: =D31*(1+F31) -> 382238.82 | H31: 2021-2025 CAGR (default)
A33: Yellow cells drive every 2026 value. Default = 2021-2025 CAGR. Overwrite with your own % (e.g. from company production guidance) to change the scenario.
A34: ConocoPhillips 2025 includes heritage Marathon Oil assets (acquired Nov-2024), so its CAGR includes a one-off step - consider lowering it.
A35: Production is a daily rate (kboe/d): the 2026 target is the average daily rate for the year.
A36: BP employees: the 2021-25 CAGR (~8.7%/yr) is driven by the jump from 68k (2022) to 100.5k (2024) and does not fit the 2025 decline; consider overriding with ~0%.

Sheet Annual_Check
A1: company | B1: year | C1: scope1_annual | D1: scope1_sum_months | E1: scope2_annual | F1: scope2_sum_months | G1: revenue_annual | H1: revenue_sum_months | I1: energy_annual | J1: energy_sum_months | K1: production_annual | L1: production_dayweighted_avg
A2: BP | B2: 2021 | C2: =Annual_Data!C2 -> 33.2 | D2: =SUMIFS(Monthly_Data!$F$2:$F$361,Monthly_Data!$A$2:$A$361,A2,Monthly_Data!$C$2:$C$361,B2) -> 33.2 | E2: =Annual_Data!D2 -> 2.4 | F2: =SUMIFS(Monthly_Data!$G$2:$G$361,Monthly_Data!$A$2:$A$361,A2,Monthly_Data!$C$2:$C$361,B2) -> 2.4 | G2: =Annual_Data!H2 -> 157739 | H2: =SUMIFS(Monthly_Data!$J$2:$J$361,Monthly_Data!$A$2:$A$361,A2,Monthly_Data!$C$2:$C$361,B2) -> 157739 | I2: =Annual_Data!I2 -> 128805 | J2: =SUMIFS(Monthly_Data!$K$2:$K$361,Monthly_Data!$A$2:$A$361,A2,Monthly_Data!$C$2:$C$361,B2) -> 128805 | K2: =Annual_Data!F2 -> 2218 | L2: =SUMPRODUCT((Monthly_Data!$A$2:$A$361=A2)*(Monthly_Data!$C$2:$C$361=B2)*Monthly_Data!$I$2:$I$361*Monthly_Data!$E$2:$E$361)/SUMIFS(Monthly_Data!$E$2:$E$361,Monthly_Data!$A$2:$A$361,A2,Monthly_Data!$C$2:$C$361,B2) -> 2218
A3: BP | B3: 2022 | C3: =Annual_Data!C3 -> 30.4 | D3: =SUMIFS(Monthly_Data!$F$2:$F$361,Monthly_Data!$A$2:$A$361,A3,Monthly_Data!$C$2:$C$361,B3) -> 30.4 | E3: =Annual_Data!D3 -> 1.4 | F3: =SUMIFS(Monthly_Data!$G$2:$G$361,Monthly_Data!$A$2:$A$361,A3,Monthly_Data!$C$2:$C$361,B3) -> 1.4 | G3: =Annual_Data!H3 -> 241392 | H3: =SUMIFS(Monthly_Data!$J$2:$J$361,Monthly_Data!$A$2:$A$361,A3,Monthly_Data!$C$2:$C$361,B3) -> 241392 | I3: =Annual_Data!I3 -> 121697 | J3: =SUMIFS(Monthly_Data!$K$2:$K$361,Monthly_Data!$A$2:$A$361,A3,Monthly_Data!$C$2:$C$361,B3) -> 121697 | K3: =Annual_Data!F3 -> 2253 | L3: =SUMPRODUCT((Monthly_Data!$A$2:$A$361=A3)*(Monthly_Data!$C$2:$C$361=B3)*Monthly_Data!$I$2:$I$361*Monthly_Data!$E$2:$E$361)/SUMIFS(Monthly_Data!$E$2:$E$361,Monthly_Data!$A$2:$A$361,A3,Monthly_Data!$C$2:$C$361,B3) -> 2253
A4: BP | B4: 2023 | C4: =Annual_Data!C4 -> 31.1 | D4: =SUMIFS(Monthly_Data!$F$2:$F$361,Monthly_Data!$A$2:$A$361,A4,Monthly_Data!$C$2:$C$361,B4) -> 31.1 | E4: =Annual_Data!D4 -> 1 | F4: =SUMIFS(Monthly_Data!$G$2:$G$361,Monthly_Data!$A$2:$A$361,A4,Monthly_Data!$C$2:$C$361,B4) -> 1 | G4: =Annual_Data!H4 -> 210130 | H4: =SUMIFS(Monthly_Data!$J$2:$J$361,Monthly_Data!$A$2:$A$361,A4,Monthly_Data!$C$2:$C$361,B4) -> 210130 | I4: =Annual_Data!I4 -> 124770 | J4: =SUMIFS(Monthly_Data!$K$2:$K$361,Monthly_Data!$A$2:$A$361,A4,Monthly_Data!$C$2:$C$361,B4) -> 124770 | K4: =Annual_Data!F4 -> 2313 | L4: =SUMPRODUCT((Monthly_Data!$A$2:$A$361=A4)*(Monthly_Data!$C$2:$C$361=B4)*Monthly_Data!$I$2:$I$361*Monthly_Data!$E$2:$E$361)/SUMIFS(Monthly_Data!$E$2:$E$361,Monthly_Data!$A$2:$A$361,A4,Monthly_Data!$C$2:$C$361,B4) -> 2313
A5: BP | B5: 2024 | C5: =Annual_Data!C5 -> 32.8 | D5: =SUMIFS(Monthly_Data!$F$2:$F$361,Monthly_Data!$A$2:$A$361,A5,Monthly_Data!$C$2:$C$361,B5) -> 32.8 | E5: =Annual_Data!D5 -> 0.8 | F5: =SUMIFS(Monthly_Data!$G$2:$G$361,Monthly_Data!$A$2:$A$361,A5,Monthly_Data!$C$2:$C$361,B5) -> 0.8 | G5: =Annual_Data!H5 -> 189185 | H5: =SUMIFS(Monthly_Data!$J$2:$J$361,Monthly_Data!$A$2:$A$361,A5,Monthly_Data!$C$2:$C$361,B5) -> 189185 | I5: =Annual_Data!I5 -> 129872 | J5: =SUMIFS(Monthly_Data!$K$2:$K$361,Monthly_Data!$A$2:$A$361,A5,Monthly_Data!$C$2:$C$361,B5) -> 129872 | K5: =Annual_Data!F5 -> 2358 | L5: =SUMPRODUCT((Monthly_Data!$A$2:$A$361=A5)*(Monthly_Data!$C$2:$C$361=B5)*Monthly_Data!$I$2:$I$361*Monthly_Data!$E$2:$E$361)/SUMIFS(Monthly_Data!$E$2:$E$361,Monthly_Data!$A$2:$A$361,A5,Monthly_Data!$C$2:$C$361,B5) -> 2358
A6: BP | B6: 2025 | C6: =Annual_Data!C6 -> 33.7 | D6: =SUMIFS(Monthly_Data!$F$2:$F$361,Monthly_Data!$A$2:$A$361,A6,Monthly_Data!$C$2:$C$361,B6) -> 33.7 | E6: =Annual_Data!D6 -> 0.7 | F6: =SUMIFS(Monthly_Data!$G$2:$G$361,Monthly_Data!$A$2:$A$361,A6,Monthly_Data!$C$2:$C$361,B6) -> 0.7 | G6: =Annual_Data!H6 -> 189335 | H6: =SUMIFS(Monthly_Data!$J$2:$J$361,Monthly_Data!$A$2:$A$361,A6,Monthly_Data!$C$2:$C$361,B6) -> 189335 | I6: =Annual_Data!I6 -> 134448 | J6: =SUMIFS(Monthly_Data!$K$2:$K$361,Monthly_Data!$A$2:$A$361,A6,Monthly_Data!$C$2:$C$361,B6) -> 134448 | K6: =Annual_Data!F6 -> 2312 | L6: =SUMPRODUCT((Monthly_Data!$A$2:$A$361=A6)*(Monthly_Data!$C$2:$C$361=B6)*Monthly_Data!$I$2:$I$361*Monthly_Data!$E$2:$E$361)/SUMIFS(Monthly_Data!$E$2:$E$361,Monthly_Data!$A$2:$A$361,A6,Monthly_Data!$C$2:$C$361,B6) -> 2312
A7: Chevron | B7: 2021 | C7: =Annual_Data!C7 -> 57 | D7: =SUMIFS(Monthly_Data!$F$2:$F$361,Monthly_Data!$A$2:$A$361,A7,Monthly_Data!$C$2:$C$361,B7) -> 57 | E7: =Annual_Data!D7 -> 2 | F7: =SUMIFS(Monthly_Data!$G$2:$G$361,Monthly_Data!$A$2:$A$361,A7,Monthly_Data!$C$2:$C$361,B7) -> 2 | G7: =Annual_Data!H7 -> 155606 | H7: =SUMIFS(Monthly_Data!$J$2:$J$361,Monthly_Data!$A$2:$A$361,A7,Monthly_Data!$C$2:$C$361,B7) -> 155606 | I7: =Annual_Data!I7 -> 205833 | J7: =SUMIFS(Monthly_Data!$K$2:$K$361,Monthly_Data!$A$2:$A$361,A7,Monthly_Data!$C$2:$C$361,B7) -> 205833 | K7: =Annual_Data!F7 -> 3099 | L7: =SUMPRODUCT((Monthly_Data!$A$2:$A$361=A7)*(Monthly_Data!$C$2:$C$361=B7)*Monthly_Data!$I$2:$I$361*Monthly_Data!$E$2:$E$361)/SUMIFS(Monthly_Data!$E$2:$E$361,Monthly_Data!$A$2:$A$361,A7,Monthly_Data!$C$2:$C$361,B7) -> 3099
A8: Chevron | B8: 2022 | C8: =Annual_Data!C8 -> 53 | D8: =SUMIFS(Monthly_Data!$F$2:$F$361,Monthly_Data!$A$2:$A$361,A8,Monthly_Data!$C$2:$C$361,B8) -> 53 | E8: =Annual_Data!D8 -> 1 | F8: =SUMIFS(Monthly_Data!$G$2:$G$361,Monthly_Data!$A$2:$A$361,A8,Monthly_Data!$C$2:$C$361,B8) -> 1 | G8: =Annual_Data!H8 -> 235717 | H8: =SUMIFS(Monthly_Data!$J$2:$J$361,Monthly_Data!$A$2:$A$361,A8,Monthly_Data!$C$2:$C$361,B8) -> 235717 | I8: =Annual_Data!I8 -> 184167 | J8: =SUMIFS(Monthly_Data!$K$2:$K$361,Monthly_Data!$A$2:$A$361,A8,Monthly_Data!$C$2:$C$361,B8) -> 184167 | K8: =Annual_Data!F8 -> 2999 | L8: =SUMPRODUCT((Monthly_Data!$A$2:$A$361=A8)*(Monthly_Data!$C$2:$C$361=B8)*Monthly_Data!$I$2:$I$361*Monthly_Data!$E$2:$E$361)/SUMIFS(Monthly_Data!$E$2:$E$361,Monthly_Data!$A$2:$A$361,A8,Monthly_Data!$C$2:$C$361,B8) -> 2999
A9: Chevron | B9: 2023 | C9: =Annual_Data!C9 -> 52 | D9: =SUMIFS(Monthly_Data!$F$2:$F$361,Monthly_Data!$A$2:$A$361,A9,Monthly_Data!$C$2:$C$361,B9) -> 52 | E9: =Annual_Data!D9 -> 1 | F9: =SUMIFS(Monthly_Data!$G$2:$G$361,Monthly_Data!$A$2:$A$361,A9,Monthly_Data!$C$2:$C$361,B9) -> 1 | G9: =Annual_Data!H9 -> 196913 | H9: =SUMIFS(Monthly_Data!$J$2:$J$361,Monthly_Data!$A$2:$A$361,A9,Monthly_Data!$C$2:$C$361,B9) -> 196913 | I9: =Annual_Data!I9 -> 185278 | J9: =SUMIFS(Monthly_Data!$K$2:$K$361,Monthly_Data!$A$2:$A$361,A9,Monthly_Data!$C$2:$C$361,B9) -> 185278 | K9: =Annual_Data!F9 -> 3120 | L9: =SUMPRODUCT((Monthly_Data!$A$2:$A$361=A9)*(Monthly_Data!$C$2:$C$361=B9)*Monthly_Data!$I$2:$I$361*Monthly_Data!$E$2:$E$361)/SUMIFS(Monthly_Data!$E$2:$E$361,Monthly_Data!$A$2:$A$361,A9,Monthly_Data!$C$2:$C$361,B9) -> 3120
A10: Chevron | B10: 2024 | C10: =Annual_Data!C10 -> 53 | D10: =SUMIFS(Monthly_Data!$F$2:$F$361,Monthly_Data!$A$2:$A$361,A10,Monthly_Data!$C$2:$C$361,B10) -> 53 | E10: =Annual_Data!D10 -> 2 | F10: =SUMIFS(Monthly_Data!$G$2:$G$361,Monthly_Data!$A$2:$A$361,A10,Monthly_Data!$C$2:$C$361,B10) -> 2 | G10: =Annual_Data!H10 -> 193414 | H10: =SUMIFS(Monthly_Data!$J$2:$J$361,Monthly_Data!$A$2:$A$361,A10,Monthly_Data!$C$2:$C$361,B10) -> 193414 | I10: =Annual_Data!I10 -> 186944 | J10: =SUMIFS(Monthly_Data!$K$2:$K$361,Monthly_Data!$A$2:$A$361,A10,Monthly_Data!$C$2:$C$361,B10) -> 186944 | K10: =Annual_Data!F10 -> 3338 | L10: =SUMPRODUCT((Monthly_Data!$A$2:$A$361=A10)*(Monthly_Data!$C$2:$C$361=B10)*Monthly_Data!$I$2:$I$361*Monthly_Data!$E$2:$E$361)/SUMIFS(Monthly_Data!$E$2:$E$361,Monthly_Data!$A$2:$A$361,A10,Monthly_Data!$C$2:$C$361,B10) -> 3338
A11: Chevron | B11: 2025 | C11: =Annual_Data!C11 -> 55 | D11: =SUMIFS(Monthly_Data!$F$2:$F$361,Monthly_Data!$A$2:$A$361,A11,Monthly_Data!$C$2:$C$361,B11) -> 55 | E11: =Annual_Data!D11 -> 2 | F11: =SUMIFS(Monthly_Data!$G$2:$G$361,Monthly_Data!$A$2:$A$361,A11,Monthly_Data!$C$2:$C$361,B11) -> 2 | G11: =Annual_Data!H11 -> 184432 | H11: =SUMIFS(Monthly_Data!$J$2:$J$361,Monthly_Data!$A$2:$A$361,A11,Monthly_Data!$C$2:$C$361,B11) -> 184432 | I11: =Annual_Data!I11 -> 197778 | J11: =SUMIFS(Monthly_Data!$K$2:$K$361,Monthly_Data!$A$2:$A$361,A11,Monthly_Data!$C$2:$C$361,B11) -> 197778 | K11: =Annual_Data!F11 -> 3723 | L11: =SUMPRODUCT((Monthly_Data!$A$2:$A$361=A11)*(Monthly_Data!$C$2:$C$361=B11)*Monthly_Data!$I$2:$I$361*Monthly_Data!$E$2:$E$361)/SUMIFS(Monthly_Data!$E$2:$E$361,Monthly_Data!$A$2:$A$361,A11,Monthly_Data!$C$2:$C$361,B11) -> 3723
A12: ConocoPhillips | B12: 2021 | C12: =Annual_Data!C12 -> 17.7 | D12: =SUMIFS(Monthly_Data!$F$2:$F$361,Monthly_Data!$A$2:$A$361,A12,Monthly_Data!$C$2:$C$361,B12) -> 17.7 | E12: =Annual_Data!D12 -> 1.03 | F12: =SUMIFS(Monthly_Data!$G$2:$G$361,Monthly_Data!$A$2:$A$361,A12,Monthly_Data!$C$2:$C$361,B12) -> 1.03 | G12: =Annual_Data!H12 -> 45828 | H12: =SUMIFS(Monthly_Data!$J$2:$J$361,Monthly_Data!$A$2:$A$361,A12,Monthly_Data!$C$2:$C$361,B12) -> 45828 | I12: =Annual_Data!I12 -> 63596 | J12: =SUMIFS(Monthly_Data!$K$2:$K$361,Monthly_Data!$A$2:$A$361,A12,Monthly_Data!$C$2:$C$361,B12) -> 63596 | K12: =Annual_Data!F12 -> 1901 | L12: =SUMPRODUCT((Monthly_Data!$A$2:$A$361=A12)*(Monthly_Data!$C$2:$C$361=B12)*Monthly_Data!$I$2:$I$361*Monthly_Data!$E$2:$E$361)/SUMIFS(Monthly_Data!$E$2:$E$361,Monthly_Data!$A$2:$A$361,A12,Monthly_Data!$C$2:$C$361,B12) -> 1901
A13: ConocoPhillips | B13: 2022 | C13: =Annual_Data!C13 -> 15 | D13: =SUMIFS(Monthly_Data!$F$2:$F$361,Monthly_Data!$A$2:$A$361,A13,Monthly_Data!$C$2:$C$361,B13) -> 15 | E13: =Annual_Data!D13 -> 1.06 | F13: =SUMIFS(Monthly_Data!$G$2:$G$361,Monthly_Data!$A$2:$A$361,A13,Monthly_Data!$C$2:$C$361,B13) -> 1.06 | G13: =Annual_Data!H13 -> 78494 | H13: =SUMIFS(Monthly_Data!$J$2:$J$361,Monthly_Data!$A$2:$A$361,A13,Monthly_Data!$C$2:$C$361,B13) -> 78494 | I13: =Annual_Data!I13 -> 60373 | J13: =SUMIFS(Monthly_Data!$K$2:$K$361,Monthly_Data!$A$2:$A$361,A13,Monthly_Data!$C$2:$C$361,B13) -> 60373 | K13: =Annual_Data!F13 -> 1885 | L13: =SUMPRODUCT((Monthly_Data!$A$2:$A$361=A13)*(Monthly_Data!$C$2:$C$361=B13)*Monthly_Data!$I$2:$I$361*Monthly_Data!$E$2:$E$361)/SUMIFS(Monthly_Data!$E$2:$E$361,Monthly_Data!$A$2:$A$361,A13,Monthly_Data!$C$2:$C$361,B13) -> 1885
... A26: ExxonMobil | B26: 2025 | C26: =Annual_Data!C26 -> 90 | D26: =SUMIFS(Monthly_Data!$F$2:$F$361,Monthly_Data!$A$2:$A$361,A26,Monthly_Data!$C$2:$C$361,B26) -> 90 | E26: =Annual_Data!D26 -> 9 | F26: =SUMIFS(Monthly_Data!$G$2:$G$361,Monthly_Data!$A$2:$A$361,A26,Monthly_Data!$C$2:$C$361,B26) -> 9 | G26: =Annual_Data!H26 -> 323905 | H26: =SUMIFS(Monthly_Data!$J$2:$J$361,Monthly_Data!$A$2:$A$361,A26,Monthly_Data!$C$2:$C$361,B26) -> 323905 | I26: =Annual_Data!I26 -> 388889 | J26: =SUMIFS(Monthly_Data!$K$2:$K$361,Monthly_Data!$A$2:$A$361,A26,Monthly_Data!$C$2:$C$361,B26) -> 388889 | K26: =Annual_Data!F26 -> 4736 | L26: =SUMPRODUCT((Monthly_Data!$A$2:$A$361=A26)*(Monthly_Data!$C$2:$C$361=B26)*Monthly_Data!$I$2:$I$361*Monthly_Data!$E$2:$E$361)/SUMIFS(Monthly_Data!$E$2:$E$361,Monthly_Data!$A$2:$A$361,A26,Monthly_Data!$C$2:$C$361,B26) -> 4736

Sheet Data_Flags
A1: company | B1: issue to check before final analysis
A2: BP | B2: Employees 2023-2025 corrected to bp Annual Report 2025 (87.8 / 100.5 / 93.7 thousand). Your file had 88 / 101 / 102 - the 2025 value of 102 does not match the report.
A3: ExxonMobil | B3: Production 2025 corrected from 4,738 to 4,736 kboe/d (Annual Report 2025).
A4: ExxonMobil | B4: Energy use is still the rounded 1.5 / 1.4 billion GJ figures, so T barely changes 2021-23 and 2024-25. Replace with more precise values if you have them.
A5: Equinor | B5: 2025 Scope 1 + 2 in this file = 10.09 Mt; Equinor reports 10.2 Mt for 2025, after a reassessment of which assets are in its operated boundary. Confirm 2025 Scope 1.
A6: Chevron | B6: Scope 2 now matches Chevron operated market-based Scope 2 (2/1/1/2/2). Column name says location-based - Chevron only reports operated location-based from 2023 (2/2/2). Note the basis in your methodology.
A7: ConocoPhillips | B7: P uses OPERATED production (matches its operated emissions and energy). Other companies only publish NET production. production_net_koebd gives the all-net alternative for a robustness check.

Sheet Method_Notes
A1: METHOD
A2: 1. Flow variables (Scope 1, Scope 2, revenue, energy): additive first-difference Denton disaggregation, weighted by days in month and a seasonal profile, so the 12 months sum exactly to the reported annual total.
A3: Scope 1 & energy seasonal profile (Jan..Dec): 1.02, 1.01, 1.00, 0.98, 0.97, 0.99, 1.01, 1.01, 0.98, 0.97, 1.01, 1.03
A4: Scope 2 seasonal profile (Jan..Dec): 1.04, 1.02, 0.99, 0.96, 0.97, 1.01, 1.05, 1.05, 1.00, 0.96, 0.98, 1.03 Revenue: days-in-month only.
A5: 2. Production (kboe/d, a daily rate): Denton on the rate so the day-weighted monthly average equals the annual average.
A6: 3. Noise: a shared company-level 'activity' shock (AR(1), sd 1.0%) moves production, energy, Scope 1 and revenue together each month, plus small variable-specific noise (seed 2026). This keeps monthly relationships between the STIRPAT drivers and emissions coherent instead of independent random noise.
A7: 4. Employees: year-end headcount, linear between Decembers (Jan-Nov 2021 back-extrapolated using the 2021-22 slope).
A8: 5. Monthly values are FORMULAS = annual value x fixed monthly share (hidden columns U-Y). Correcting a number in Annual_Data updates every month automatically and keeps annual totals exact.
A9: 6. 2026 (synthetic): target = 2025 x (1 + growth) from Assumptions_2026; monthly path continues from the Dec-2025 level with the same seasonality and noise.
A10: 7. STIRPAT columns: P = production, A = revenue, T = energy intensity (GWh per million boe). ln_ columns are natural logs ready for the log-linear STIRPAT regression. post_acquisition is a step dummy for major acquisitions.
A11: 8. Definitions (verified against company filings, see Changes_Log): A = sales and other operating revenues (Equinor: 'Revenues' line), excluding other income and equity-affiliate income. P = net oil-equivalent production, except ConocoPhillips = operated production.
A13: IMPORTANT FOR YOUR ANALYSIS
... A18: COLOUR KEY: blue = your input | green = link to another sheet | black = formula | yellow = editable assumption / synthetic rows | grey = hidden helper shares
